{"plain": "Based on the user's favourite books, it can be inferred that the user enjoys reading books with the following characteristics:\n\nGenre: The user seems to have a preference for fiction books, as both \"Animal Farm\" and \"The Catcher in the Rye\" are novels.\n\nPlot: The user appears to enjoy books with complex and thought-provoking plots, as both \"Animal Farm\" and \"The Catcher in the Rye\" deal with important social and political issues.\n\nSetting: The user seems to have a preference for books set in different times and places, as \"Animal Farm\" is a satirical take on the Russian Revolution and \"The Catcher in the Rye\" is set in New York City in the 1950s.\n\nWriting Style: The user seems to enjoy books with a unique and engaging writing style, as both \"Animal Farm\" and \"The Catcher in the Rye\" are known for their distinct voices and perspectives.\n\nLength: The user does not seem to have a preference for a specific length of book, as both \"Animal Farm\" and \"The Catcher in the Rye\" are of different lengths.\n\nTopic: The user appears to have a preference for books that tackle important social and political issues, as both \"Animal Farm\" and \"The Catcher in the Rye\" deal with these themes.\n\nPacing: The user seems to enjoy books with a good pace, as both \"Animal Farm\" and \"The Catcher in the Rye\" are known for their engaging and fast-paced narratives.\n\nNarrative Structure: The user seems to enjoy books with a clear and well-crafted narrative structure, as both \"Animal Farm\" and \"The Catcher in the Rye\" are well-structured and easy to follow.\n\nThemes: The user appears to have a preference for books that deal with themes of rebellion, social commentary, and coming-of-age, as both \"Animal Farm\" and \"The Catcher in the Rye\" tackle these themes.\n\nBased on the user's preferences, it can be inferred that the user enjoys reading books that are thought-provoking, engaging, and well-crafted, regardless of genre or length. The user's taste seems to be diverse and open to a wide range of topics and perspectives, which suggests a love for literature and a desire to explore new ideas and experiences through reading.", "based on the user's favourite books, it can be inferred that the user enjoys reading books with the following characteristics:\n\ngenre": ["the user seems to have a preference for fiction books", "as both \"animal farm\" and \"the catcher in the rye\" are novels"], "plot": ["the user appears to enjoy books with complex and thought-provoking plots", "as both \"animal farm\" and \"the catcher in the rye\" deal with important social and political issues"], "setting": ["the user seems to have a preference for books set in different times and places", "as \"animal farm\" is a satirical take on the russian revolution and \"the catcher in the rye\" is set in new york city in the 1950s"], "writing style": ["the user seems to enjoy books with a unique and engaging writing style", "as both \"animal farm\" and \"the catcher in the rye\" are known for their distinct voices and perspectives"], "length": ["the user does not seem to have a preference for a specific length of book", "as both \"animal farm\" and \"the catcher in the rye\" are of different lengths"], "topic": ["the user appears to have a preference for books that tackle important social and political issues", "as both \"animal farm\" and \"the catcher in the rye\" deal with these themes"], "pacing": ["the user seems to enjoy books with a good pace", "as both \"animal farm\" and \"the catcher in the rye\" are known for their engaging and fast-paced narratives"], "narrative structure": ["the user seems to enjoy books with a clear and well-crafted narrative structure", "as both \"animal farm\" and \"the catcher in the rye\" are well-structured and easy to follow"], "themes": ["the user appears to have a preference for books that deal with themes of rebellion", "social commentary", "and coming-of-age", "as both \"animal farm\" and \"the catcher in the rye\" tackle these themes"]}