{"plain": "Based on the user's favourite books, it can be inferred that the user enjoys reading books that are:\n- Character-driven: The books feature complex and relatable characters that drive the plot forward.\n- Multilayered: The books explore multiple themes and topics, such as mental health, family dynamics, and social commentary.\n- Thought-provoking: The books challenge the reader to think critically about the world and the characters within it.\n- Well-written: The books feature well-crafted prose and dialogue that enhance the reading experience.\n\nIt can also be inferred that the user enjoys reading books that are:\n- Realistic: The books are set in contemporary times and explore relatable themes and situations.\n- Emotional: The books evoke strong emotions in the reader, such as empathy, sadness, and joy.\n- Accessible: The books are written in a way that is easy to understand and relate to, regardless of the reader's background.\n\nIn summary, the user's taste in books can be described as a preference for character-driven, multilayered, thought-provoking, and well-written stories that are realistic, emotional, and accessible.", "based on the user's favourite books, it can be inferred that the user enjoys reading books that are:\n- character-driven": ["the books feature complex and relatable characters that drive the plot forward"], "- multilayered": ["the books explore multiple themes and topics", "such as mental health", "family dynamics", "and social commentary"], "- thought-provoking": ["the books challenge the reader to think critically about the world and the characters within it"], "- well-written": ["the books feature well-crafted prose and dialogue that enhance the reading experience"], "it can also be inferred that the user enjoys reading books that are:\n- realistic": ["the books are set in contemporary times and explore relatable themes and situations"], "- emotional": ["the books evoke strong emotions in the reader", "such as empathy", "sadness", "and joy"], "- accessible": ["the books are written in a way that is easy to understand and relate to", "regardless of the reader's background"]}