{"plain": "Based on the user's favourite books, it can be inferred that the user enjoys reading books that are:\n- Character-driven: The user enjoys books that focus on the development and exploration of complex characters.\n- Multilayered: The user enjoys books that have multiple layers of meaning and exploration.\n- Thought-provoking: The user enjoys books that challenge their assumptions and make them think about important topics.\n- Well-written: The user enjoys books that are written with a high level of skill and craftsmanship.\n- Engaging: The user enjoys books that are able to keep their attention and interest throughout the entire story.\n\nBased on the user's favourite books, it can be inferred that the user enjoys reading books that are:\n- Character-driven: The user enjoys books that focus on the development and exploration of complex characters.\n- Multilayered: The user enjoys books that have multiple layers of meaning and exploration.\n- Thought-provoking: The user enjoys books that challenge their assumptions and make them think about important topics.\n- Well-written: The user enjoys books that are written with a high level of skill and craftsmanship.\n- Engaging: The user enjoys books that are able to keep their attention and interest throughout the entire story.\n\nBased on the user's favourite books, it can be inferred that the user enjoys reading books that are:\n- Character-driven: The user enjoys books that focus on the development and exploration of complex characters.\n- Multilayered: The user enjoys books that have multiple layers of meaning and exploration.\n- Thought-provoking: The user enjoys books that challenge their assumptions and make them think about important topics.\n- Well-written: The user enjoys books that are written with a high level of skill and craftsmanship.\n- Engaging: The user enjoys books that are able to keep their attention and interest throughout the entire story.\n\nBased on the user's favourite books, it can be inferred that the user enjoys reading books that are:\n- Character-driven: The user enjoys books that focus on the development and exploration of complex characters.\n- Multilayered: The user enjoys books that have multiple layers of meaning and exploration.\n- Thought-provoking: The user enjoys books that challenge their assumptions and make them think about important topics.\n- Well-written: The user enjoys books that are written with a high level of skill and craftsmanship.\n- Engaging: The user enjoys books that are able to keep their attention and interest throughout the entire story.\n\nBased on the user's favourite books, it can be inferred that the user enjoys reading books that are", "based on the user's favourite books, it can be inferred that the user enjoys reading books that are:\n- character-driven": ["the user enjoys books that focus on the development and exploration of complex characters"], "- multilayered": ["the user enjoys books that have multiple layers of meaning and exploration"], "- thought-provoking": ["the user enjoys books that challenge their assumptions and make them think about important topics"], "- well-written": ["the user enjoys books that are written with a high level of skill and craftsmanship"], "- engaging": ["the user enjoys books that are able to keep their attention and interest throughout the entire story"]}