{"plain": "The user's favourite genre is likely to be crime fiction, as the book \"Theft: A Love Story\" falls under this genre. The user's favourite kind of plot is likely to be complex and multi-layered, as the book \"Theft: A Love Story\" features a intricate narrative with multiple subplots. The user's favourite setting is likely to be urban, as the book \"Theft: A Love Story\" is set in a city. The user's favourite writing style is likely to be descriptive and vivid, as the book \"Theft: A Love Story\" features richly drawn scenes and characters. The user's favourite length is likely to be novel-length, as the book \"Theft: A Love Story\" is a full-length novel. The user's favourite topic is likely to be crime and justice, as the book \"Theft: A Love Story\" explores these themes in depth. The user's favourite pacing is likely to be slow and methodical, as the book \"Theft: A Love Story\" takes its time to develop its story and characters. The user's favourite narrative structure is likely to be non-linear, as the book \"Theft: A Love Story\" features a non-chronological narrative that jumps back and forth in time. The user's favourite themes are likely to be crime, justice, and morality, as the book \"Theft: A Love Story\" explores these themes in depth.", "the user's favourite genre is likely to be crime fiction, as the book \"theft": ["a love story\" falls under this genre"], "the user's favourite kind of plot is likely to be complex and multi-layered, as the book \"theft": ["a love story\" features a intricate narrative with multiple subplots"], "the user's favourite setting is likely to be urban, as the book \"theft": ["a love story\" is set in a city"], "the user's favourite writing style is likely to be descriptive and vivid, as the book \"theft": ["a love story\" features richly drawn scenes and characters"], "the user's favourite length is likely to be novel-length, as the book \"theft": ["a love story\" is a full-length novel"], "the user's favourite topic is likely to be crime and justice, as the book \"theft": ["a love story\" explores these themes in depth"], "the user's favourite pacing is likely to be slow and methodical, as the book \"theft": ["a love story\" takes its time to develop its story and characters"], "the user's favourite narrative structure is likely to be non-linear, as the book \"theft": ["a love story\" features a non-chronological narrative that jumps back and forth in time"], "the user's favourite themes are likely to be crime, justice, and morality, as the book \"theft": ["a love story\" explores these themes in depth"]}