{"plain": "Based on the user's favourite books, it can be inferred that the user enjoys reading books that are:\n- Non-fiction: The Rise and Fall of the Great Powers, A History of God, and A Short History of Nearly Everything are all non-fiction books.\n- Fantasy: The Conquering Sword of Conan and Vimanarama are both fantasy books.\n- Science Fiction: Universe is a science fiction book.\n\nIt can also be inferred that the user enjoys reading books that are:\n- Well-researched and informative: The Rise and Fall of the Great Powers, A History of God, and A Short History of Nearly Everything are all well-researched and informative books.\n- Imaginative and creative: The Conquering Sword of Conan, Vimanarama, and Universe are all imaginative and creative books.\n\nIn terms of the user's favourite themes, it can be inferred that the user enjoys reading books that explore themes of:\n- History and politics: The Rise and Fall of the Great Powers explores themes of history and politics.\n- Religion and spirituality: A History of God explores themes of religion and spirituality.\n- Science and the universe: A Short History of Nearly Everything explores themes of science and the universe.\n- Fantasy and imagination: The Conquering Sword of Conan, Vimanarama, and Universe all explore themes of fantasy and imagination.\n\nOverall, it can be inferred that the user has a diverse and eclectic taste in reading, enjoying books that are both informative and imaginative, and exploring a wide range of themes and genres.", "based on the user's favourite books, it can be inferred that the user enjoys reading books that are:\n- non-fiction": ["the rise and fall of the great powers", "a history of god", "and a short history of nearly everything are all non-fiction books"], "- fantasy": ["the conquering sword of conan and vimanarama are both fantasy books"], "- science fiction": ["universe is a science fiction book"], "it can also be inferred that the user enjoys reading books that are:\n- well-researched and informative": ["the rise and fall of the great powers", "a history of god", "and a short history of nearly everything are all well-researched and informative books"], "- imaginative and creative": ["the conquering sword of conan", "vimanarama", "and universe are all imaginative and creative books"], "in terms of the user's favourite themes, it can be inferred that the user enjoys reading books that explore themes of:\n- history and politics": ["the rise and fall of the great powers explores themes of history and politics"], "- religion and spirituality": ["a history of god explores themes of religion and spirituality"], "- science and the universe": ["a short history of nearly everything explores themes of science and the universe"], "- fantasy and imagination": ["the conquering sword of conan", "vimanarama", "and universe all explore themes of fantasy and imagination"]}