{"plain": "Based on the user's favourite books, it can be inferred that the user enjoys:\n- Literary fiction: The History of Love and The Corrections are examples of this genre.\n- Mystery: Case Histories and The Curious Incident of the Dog in the Night-Time are mystery novels.\n- Humor: Me Talk Pretty One Day is a humorous book.\n- Writing style: The user seems to enjoy books with a unique and engaging writing style.\n\nIt can also be inferred that the user enjoys:\n- Complex plots: The user seems to enjoy books with intricate and multi-layered plots.\n- Character-driven stories: The user seems to enjoy books that focus on the development of characters.\n- Thought-provoking themes: The user seems to enjoy books that tackle important social and philosophical issues.\n\nIn summary, the user seems to enjoy literary fiction, mystery, humor, and character-driven stories with complex plots and thought-provoking themes. The user also seems to appreciate unique and engaging writing styles.", "based on the user's favourite books, it can be inferred that the user enjoys:\n- literary fiction": ["the history of love and the corrections are examples of this genre"], "- mystery": ["case histories and the curious incident of the dog in the night-time are mystery novels"], "- humor": ["me talk pretty one day is a humorous book"], "- writing style": ["the user seems to enjoy books with a unique and engaging writing style"], "it can also be inferred that the user enjoys:\n- complex plots": ["the user seems to enjoy books with intricate and multi-layered plots"], "- character-driven stories": ["the user seems to enjoy books that focus on the development of characters"], "- thought-provoking themes": ["the user seems to enjoy books that tackle important social and philosophical issues"]}