{"plain": "Based on the user's favorite books, it can be inferred that they enjoy reading works with a combination of the following features:\n\n    Genre: Realistic fiction, dystopian fiction, and short story collection.\n    Plot: Complex and multi-layered, often exploring themes of tragedy, love, and social commentary.\n    Setting: Rural New England, a fictional island nation, and urban America.\n    Writing Style: Stream-of-consciousness, poetic, and minimalist.\n    Length: Novels, novellas, and short stories.\n    Topic: Human relationships, societal constraints, and the human condition.\n    Pacing: Slow and contemplative, with a focus on character development and atmosphere.\n    Narrative Structure: Non-linear, with a focus on the impact of past events on the present.\n    Themes: Tragedy, love, and social commentary.\n\nIt can also be inferred that the user enjoys reading works that challenge conventional narrative structures and explore complex themes through a combination of literary devices and unique storytelling techniques.", "based on the user's favorite books, it can be inferred that they enjoy reading works with a combination of the following features:\n\n    genre": ["realistic fiction", "dystopian fiction", "and short story collection"], "plot": ["complex and multi-layered", "often exploring themes of tragedy", "love", "and social commentary"], "setting": ["rural new england", "a fictional island nation", "and urban america"], "writing style": ["stream-of-consciousness", "poetic", "and minimalist"], "length": ["novels", "novellas", "and short stories"], "topic": ["human relationships", "societal constraints", "and the human condition"], "pacing": ["slow and contemplative", "with a focus on character development and atmosphere"], "narrative structure": ["non-linear", "with a focus on the impact of past events on the present"], "themes": ["tragedy", "love", "and social commentary"]}