{"plain": "Based on the user's favourite books, it can be inferred that the user enjoys:\n- Literary fiction: Both \"I Know This Much is True\" and \"The Broker\" are considered literary fiction, known for their complex characters and themes.\n- Complex characters: Both books feature complex and multi-dimensional characters, which the user seems to enjoy.\n- Themes of mental health and family: \"I Know This Much is True\" explores themes of mental health and family, which the user seems to appreciate.\n- Political intrigue: \"The Broker\" delves into the world of political intrigue, which the user seems to find engaging.\n\nBased on the user's preferences, it can be inferred that the user enjoys:\n- Well-crafted storytelling: Both books are known for their well-crafted storytelling, which the user seems to appreciate.\n- Complex plots: Both books feature complex plots, which the user seems to enjoy.\n- Richly developed settings: \"The Broker\" is set in the world of international politics, while \"I Know This Much is True\" is set in the world of mental health and family, both of which the user seems to find engaging.\n\nBased on the user's preferences, it can be inferred that the user enjoys:\n- Thought-provoking themes: Both books explore thought-provoking themes, which the user seems to appreciate.\n- Emotional depth: Both books delve into emotional depth, which the user seems to find engaging.\n- Compelling narratives: Both books feature compelling narratives, which the user seems to enjoy.\n\nIn summary, based on the user's favourite books, it can be inferred that the user enjoys literary fiction, complex characters, themes of mental health and family, political intrigue, well-crafted storytelling, complex plots, richly developed settings, thought-provoking themes, emotional depth, and compelling narratives.", "based on the user's favourite books, it can be inferred that the user enjoys:\n- literary fiction": ["both \"i know this much is true\" and \"the broker\" are considered literary fiction", "known for their complex characters and themes"], "- complex characters": ["both books feature complex and multi-dimensional characters", "which the user seems to enjoy"], "- themes of mental health and family": ["\"i know this much is true\" explores themes of mental health and family", "which the user seems to appreciate"], "- political intrigue": ["\"the broker\" delves into the world of political intrigue", "which the user seems to find engaging"], "based on the user's preferences, it can be inferred that the user enjoys:\n- well-crafted storytelling": ["both books are known for their well-crafted storytelling", "which the user seems to appreciate"], "- complex plots": ["both books feature complex plots", "which the user seems to enjoy"], "- richly developed settings": ["\"the broker\" is set in the world of international politics", "while \"i know this much is true\" is set in the world of mental health and family", "both of which the user seems to find engaging"], "based on the user's preferences, it can be inferred that the user enjoys:\n- thought-provoking themes": ["both books explore thought-provoking themes", "which the user seems to appreciate"], "- emotional depth": ["both books delve into emotional depth", "which the user seems to find engaging"], "- compelling narratives": ["both books feature compelling narratives", "which the user seems to enjoy"]}