{"plain": "Based on the user's favourite books, it can be inferred that the user enjoys reading books with a combination of the following features:\n\nGenre: Fiction, especially coming-of-age stories and biographies.\nPlot: The user enjoys stories that are both entertaining and thought-provoking, with a focus on character development and emotional depth.\nSetting: The user enjoys stories that take place in a variety of settings, including contemporary urban settings and historical contexts.\nWriting Style: The user enjoys a variety of writing styles, including narrative, descriptive, and dialogue-driven prose.\nLength: The user enjoys books of varying lengths, from short novellas to longer epics.\nTopic: The user enjoys books that explore a wide range of topics, including personal growth, social justice, and historical events.\nPacing: The user enjoys a balance of action and reflection, with a focus on the emotional journey of the characters.\nNarrative Structure: The user enjoys a variety of narrative structures, including linear, non-linear, and experimental approaches.\nThemes: The user enjoys books that explore themes of self-discovery, personal growth, and social justice.\n\nBased on the user's taste, it can be inferred that they enjoy reading books that challenge them intellectually and emotionally, while also being entertaining and accessible. They appreciate a wide range of writing styles and narrative structures, and are not limited to any specific genre or topic. Their reading preferences suggest a curiosity about the world and a desire to learn from the experiences of others.", "based on the user's favourite books, it can be inferred that the user enjoys reading books with a combination of the following features:\n\ngenre": ["fiction", "especially coming-of-age stories and biographies"], "plot": ["the user enjoys stories that are both entertaining and thought-provoking", "with a focus on character development and emotional depth"], "setting": ["the user enjoys stories that take place in a variety of settings", "including contemporary urban settings and historical contexts"], "writing style": ["the user enjoys a variety of writing styles", "including narrative", "descriptive", "and dialogue-driven prose"], "length": ["the user enjoys books of varying lengths", "from short novellas to longer epics"], "topic": ["the user enjoys books that explore a wide range of topics", "including personal growth", "social justice", "and historical events"], "pacing": ["the user enjoys a balance of action and reflection", "with a focus on the emotional journey of the characters"], "narrative structure": ["the user enjoys a variety of narrative structures", "including linear", "non-linear", "and experimental approaches"], "themes": ["the user enjoys books that explore themes of self-discovery", "personal growth", "and social justice"]}