{"plain": "The user's favourite genre is fantasy, as evidenced by the inclusion of \"Jonathan Strange & Mr Norrell\" and \"Good Omens\" in their list. Both of these books are set in an alternative version of history, with supernatural elements. Additionally, \"The Sandman: The Dream Hunters\" and \"The Man Who Was Thursday\" both contain elements of the supernatural, further supporting the user's preference for fantasy.\n\nThe user's favourite kind of plot is likely to be complex and multi-layered, as evidenced by the inclusion of \"Jonathan Strange & Mr Norrell\" and \"The Man Who Was Thursday\" in their list. Both of these books feature intricate plots with many twists and turns. Additionally, \"Good Omens\" and \"The Sandman: The Dream Hunters\" both have complex plots, further supporting the user's preference for complex and multi-layered plots.\n\nThe user's favourite setting is likely to be an alternative version of history, as evidenced by the inclusion of \"Jonathan Strange & Mr Norrell\" and \"Good Omens\" in their list. Both of these books are set in an alternative version of history, with supernatural elements. Additionally, \"The Sandman: The Dream Hunters\" and \"The Man Who Was Thursday\" both contain elements of the supernatural, further supporting the user's preference for alternative versions of history as a setting.\n\nThe user's favourite writing style is likely to be descriptive and imaginative, as evidenced by the inclusion of \"Jonathan Strange & Mr Norrell\" and \"The Sandman: The Dream Hunters\" in their list. Both of these books are known for their descriptive and imaginative writing styles. Additionally, \"Good Omens\" and \"The Man Who Was Thursday\" both have imaginative and creative writing styles, further supporting the user's preference for descriptive and imaginative writing styles.\n\nThe user's favourite length is likely to be longer, as evidenced by the inclusion of \"Jonathan Strange & Mr Norrell\" and \"The Sandman: The Dream Hunters\" in their list. Both of these books are quite long, with \"Jonathan Strange & Mr Norrell\" being particularly lengthy. Additionally, \"Good Omens\" and \"The Man Who Was Thursday\" are both longer books, further supporting the user's preference for longer books.\n\nThe user's favourite topic is likely to be supernatural or fantasy-related, as evidenced by the inclusion of \"Jonathan Strange & Mr Norrell\" and \"The Sandman: The Dream Hunters\" in their list. Both of these books contain supernatural elements, and \"The Man Who Was Thursday", "additionally, \"the sandman": ["the dream hunters\" and \"the man who was thursday\" both contain elements of the supernatural", "further supporting the user's preference for alternative versions of history as a setting"], "additionally, \"good omens\" and \"the sandman": ["the dream hunters\" both have complex plots", "further supporting the user's preference for complex and multi-layered plots"], "the user's favourite writing style is likely to be descriptive and imaginative, as evidenced by the inclusion of \"jonathan strange & mr norrell\" and \"the sandman": ["the dream hunters\" in their list"], "the user's favourite length is likely to be longer, as evidenced by the inclusion of \"jonathan strange & mr norrell\" and \"the sandman": ["the dream hunters\" in their list"], "the user's favourite topic is likely to be supernatural or fantasy-related, as evidenced by the inclusion of \"jonathan strange & mr norrell\" and \"the sandman": ["the dream hunters\" in their list"]}