{"plain": "Based on the user's favourite books, it can be inferred that the user enjoys reading books that are:\n- Adventure/Fantasy: The Princess Bride is a well-known adventure fantasy novel, while On the Banks of Plum Creek is a classic children's book that also contains elements of adventure and fantasy.\n- Well-written: Both books are highly regarded for their writing style, which is likely to be a factor in the user's enjoyment.\n- Engaging: Both books are known for their engaging plots and characters, which keep readers interested and invested in the story.\n\nIt can also be inferred that the user enjoys reading books that are:\n- Children's/Young Adult: On the Banks of Plum Creek is a classic children's book, and The Princess Bride has been adapted into a popular children's movie.\n- Classic: Both books are considered classics in their respective genres, and have stood the test of time.\n- Well-crafted: Both books are highly regarded for their writing style, which is likely to be a factor in the user's enjoyment.\n- Engaging: Both books are known for their engaging plots and characters, which keep readers interested and invested in the story.\n\nIn summary, based on the user's favourite books, it can be inferred that the user enjoys reading books that are well-written, engaging, and well-crafted, and that they have a preference for children's/young adult and classic literature.", "based on the user's favourite books, it can be inferred that the user enjoys reading books that are:\n- adventure/fantasy": ["the princess bride is a well-known adventure fantasy novel", "while on the banks of plum creek is a classic children's book that also contains elements of adventure and fantasy"], "- well-written": ["both books are highly regarded for their writing style", "which is likely to be a factor in the user's enjoyment"], "- engaging": ["both books are known for their engaging plots and characters", "which keep readers interested and invested in the story"], "it can also be inferred that the user enjoys reading books that are:\n- children's/young adult": ["on the banks of plum creek is a classic children's book", "and the princess bride has been adapted into a popular children's movie"], "- classic": ["both books are considered classics in their respective genres", "and have stood the test of time"], "- well-crafted": ["both books are highly regarded for their writing style", "which is likely to be a factor in the user's enjoyment"]}