{"plain": "Based on the user's favourite books, it can be inferred that the user enjoys reading books that are:\n- Literary fiction: The user's favourites include \"Another Country\", \"In Another Country\", and \"The Book of Laughter and Forgetting\", which are all considered literary fiction.\n- Coming-of-age: \"The Catcher in the Rye\" is a classic coming-of-age novel.\n- Realistic: The user's favourites seem to be set in real-world locations and deal with relatable themes.\n- Character-driven: The user's favourites seem to focus on complex characters and their development over the course of the story.\n\nIt can also be inferred that the user enjoys reading books that are:\n- Well-written: The user's favourites seem to be well-crafted and expertly executed.\n- Thought-provoking: The user's favourites seem to be books that make the user think and reflect on life.\n- Emotional: The user's favourites seem to be books that evoke strong emotions and connect with the user on a deep, personal level.\n\nIn summary, the user appears to have a refined and sophisticated taste in literature, enjoying books that are literary fiction, character-driven, well-written, thought-provoking, and emotional. The user's favourites seem to be set in real-world locations and deal with relatable themes, making them accessible and relatable to a wide audience.", "based on the user's favourite books, it can be inferred that the user enjoys reading books that are:\n- literary fiction": ["the user's favourites include \"another country\"", "\"in another country\"", "and \"the book of laughter and forgetting\"", "which are all considered literary fiction"], "- coming-of-age": ["\"the catcher in the rye\" is a classic coming-of-age novel"], "- realistic": ["the user's favourites seem to be set in real-world locations and deal with relatable themes"], "- character-driven": ["the user's favourites seem to focus on complex characters and their development over the course of the story"], "it can also be inferred that the user enjoys reading books that are:\n- well-written": ["the user's favourites seem to be well-crafted and expertly executed"], "- thought-provoking": ["the user's favourites seem to be books that make the user think and reflect on life"], "- emotional": ["the user's favourites seem to be books that evoke strong emotions and connect with the user on a deep", "personal level"]}