{"plain": "Based on the user's favorite books, it can be inferred that they enjoy reading books that are:\n- Non-fiction: All of the books mentioned are non-fiction, with a focus on science, anthropology, and science fiction.\n- Thought-provoking: All of the books mentioned are known for their unique and thought-provoking perspectives.\n- Well-researched: All of the books mentioned are known for their thorough research and attention to detail.\n\nIt can also be inferred that the user enjoys reading books that are:\n- Complex: All of the books mentioned are known for their complexity and depth of content.\n- Multi-layered: All of the books mentioned are known for their multi-layered approach to exploring various topics and ideas.\n\nIn terms of specific themes, it can be inferred that the user enjoys reading books that explore the intersection of science, technology, and human nature. Additionally, the user may have an interest in topics related to anthropology, linguistics, and the study of culture.\n\nOverall, the user's taste in books appears to be highly intellectual, with a focus on non-fiction works that offer a unique and thought-provoking perspective on various topics and ideas.", "based on the user's favorite books, it can be inferred that they enjoy reading books that are:\n- non-fiction": ["all of the books mentioned are non-fiction", "with a focus on science", "anthropology", "and science fiction"], "- thought-provoking": ["all of the books mentioned are known for their unique and thought-provoking perspectives"], "- well-researched": ["all of the books mentioned are known for their thorough research and attention to detail"], "it can also be inferred that the user enjoys reading books that are:\n- complex": ["all of the books mentioned are known for their complexity and depth of content"], "- multi-layered": ["all of the books mentioned are known for their multi-layered approach to exploring various topics and ideas"]}