{"plain": "The user's favourite genre is likely fantasy, as both \"The Light Fantastic\" and \"Waylander II: In the Realm of the Wolf\" are fantasy novels. The user's favourite kind of plot is likely adventure, as both \"The Light Fantastic\" and \"Waylander II: In the Realm of the Wolf\" feature adventure elements. The user's favourite setting is likely a fictional world, as both \"The Light Fantastic\" and \"Waylander II: In the Realm of the Wolf\" are set in fictional worlds. The user's favourite writing style is likely descriptive, as both \"The Light Fantastic\" and \"Waylander II: In the Realm of the Wolf\" feature descriptive prose. The user's favourite length is likely novel-length, as both \"The Light Fantastic\" and \"Waylander II: In the Realm of the Wolf\" are novels. The user's favourite topic is likely magic, as \"The Light Fantastic\" features magic as a central theme. The user's favourite pacing is likely fast-paced, as both \"The Light Fantastic\" and \"Waylander II: In the Realm of the Wolf\" feature action-packed scenes. The user's favourite narrative structure is likely third-person omniscient, as both \"The Light Fantastic\" and \"Waylander II: In the Realm of the Wolf\" are written in this style. The user's favourite themes are likely adventure, magic, and coming-of-age, as these themes are all present in \"The Light Fantastic\" and \"Waylander II: In the Realm of the Wolf\".", "the user's favourite genre is likely fantasy, as both \"the light fantastic\" and \"waylander ii": ["in the realm of the wolf\" are fantasy novels"], "the user's favourite kind of plot is likely adventure, as both \"the light fantastic\" and \"waylander ii": ["in the realm of the wolf\" feature adventure elements"], "the user's favourite setting is likely a fictional world, as both \"the light fantastic\" and \"waylander ii": ["in the realm of the wolf\" are set in fictional worlds"], "the user's favourite writing style is likely descriptive, as both \"the light fantastic\" and \"waylander ii": ["in the realm of the wolf\" feature descriptive prose"], "the user's favourite length is likely novel-length, as both \"the light fantastic\" and \"waylander ii": ["in the realm of the wolf\" are novels"], "the user's favourite pacing is likely fast-paced, as both \"the light fantastic\" and \"waylander ii": ["in the realm of the wolf\" feature action-packed scenes"], "the user's favourite narrative structure is likely third-person omniscient, as both \"the light fantastic\" and \"waylander ii": ["in the realm of the wolf\" are written in this style"], "the user's favourite themes are likely adventure, magic, and coming-of-age, as these themes are all present in \"the light fantastic\" and \"waylander ii": ["in the realm of the wolf\""]}