{"plain": "Based on the user's favorite books, it can be inferred that they enjoy reading a variety of genres, including fiction (Prince Caspian), non-fiction (A Grief Observed), and fantasy/science fiction (Red Dwarf: Infinity Welcomes Careful Drivers). They also seem to appreciate well-crafted writing, as evidenced by the inclusion of both classic literature (A Grief Observed) and modern fiction (Red Dwarf: Infinity Welcomes Careful Drivers).\n\nIn terms of plot, the user appears to have a preference for complex, multi-layered stories that explore deep themes and offer thought-provoking commentary on society. This is evident in the choice of A Monstrous Regiment of Women, which delves into issues of gender and power, and Red Dwarf: Infinity Welcomes Careful Drivers, which uses science fiction to explore themes of identity and the human condition.\n\nAs for setting, the user seems to have a fondness for imaginative, alternate worlds, as seen in the choice of Red Dwarf: Infinity Welcomes Careful Drivers. However, they also appreciate the beauty and complexity of the real world, as evidenced by the inclusion of A Grief Observed, which explores the depths of human emotion and experience.\n\nIn terms of writing style, the user appears to have a preference for authors who are skilled in crafting engaging, well-written prose. Both A Grief Observed and Red Dwarf: Infinity Welcomes Careful Drivers are examples of this, with the former being known for its poetic, introspective tone and the latter for its clever, humorous dialogue and descriptions.\n\nAs for length, the user seems to have no preference, as they have chosen books of varying lengths, from the relatively short Red Dwarf: Infinity Welcomes Careful Drivers to the longer A Grief Observed.\n\nIn terms of topic, the user appears to have a fondness for books that explore deep, thought-provoking themes, such as identity, society, and the human condition. This is evident in the choice of Red Dwarf: Infinity Welcomes Careful Drivers, which uses science fiction to explore these themes, and A Monstrous Regiment of Women, which delves into issues of gender and power.\n\nAs for pacing, the user seems to have a preference for books that are well-paced and offer a balance of action and reflection. Both A Grief Observed and Red Dwarf: Infinity Welcomes Careful Drivers are examples of this, with the former offering a slow, introspective exploration of grief and the latter offering a balance of humorous dialogue and thoughtful", "based on the user's favorite books, it can be inferred that they enjoy reading a variety of genres, including fiction (prince caspian), non-fiction (a grief observed), and fantasy/science fiction (red dwarf": ["infinity welcomes careful drivers)"], "they also seem to appreciate well-crafted writing, as evidenced by the inclusion of both classic literature (a grief observed) and modern fiction (red dwarf": ["infinity welcomes careful drivers)"], "this is evident in the choice of a monstrous regiment of women, which delves into issues of gender and power, and red dwarf": ["infinity welcomes careful drivers", "which uses science fiction to explore themes of identity and the human condition"], "as for setting, the user seems to have a fondness for imaginative, alternate worlds, as seen in the choice of red dwarf": ["infinity welcomes careful drivers"], "both a grief observed and red dwarf": ["infinity welcomes careful drivers are examples of this", "with the former offering a slow", "introspective exploration of grief and the latter offering a balance of humorous dialogue and thoughtful"], "as for length, the user seems to have no preference, as they have chosen books of varying lengths, from the relatively short red dwarf": ["infinity welcomes careful drivers to the longer a grief observed"], "this is evident in the choice of red dwarf": ["infinity welcomes careful drivers", "which uses science fiction to explore these themes", "and a monstrous regiment of women", "which delves into issues of gender and power"]}