{"plain": "Based on the list of favorite books provided, the following inferences can be made about the user's taste:\n\n1. Favorite Genre: The user seems to have a preference for fiction, as most of the books listed fall under this category. Specifically, the user appears to enjoy classic literature, as many of the titles are well-known works from the 19th and early 20th centuries.\n\n2. Favorite Plot: The user seems to have a preference for complex, multi-layered plots, as many of the books listed feature intricate storylines with multiple subplots and character motivations.\n\n3. Favorite Setting: The user appears to enjoy a variety of settings, ranging from fictional fantasy worlds to historical and maritime settings.\n\n4. Favorite Writing Style: The user seems to appreciate a range of writing styles, from the lyrical and descriptive prose of authors like Tolstoy and James to the more straightforward and narrative-driven style of authors like Stevenson and Hemingway.\n\n5. Favorite Length: The user appears to have no preference for length, as the list includes books of varying lengths, from short novellas to longer epics.\n\n6. Favorite Topic: The user seems to have a particular interest in themes of love, family, and social commentary, as many of the books listed tackle these subjects in some way.\n\n7. Favorite Pacing: The user appears to enjoy a range of pacing, from the fast-paced action of \"A Night to Remember\" to the slower, more introspective pacing of \"Doctor Zhivago.\"\n\n8. Favorite Narrative Structure: The user appears to enjoy a variety of narrative structures, from the linear and chronological structure of \"Anna Karenina\" to the more nonlinear and experimental structure of \"The Master and Margarita.\"\n\n9. Favorite Themes: The user appears to have a particular interest in themes of morality, spirituality, and the human condition, as many of the books listed tackle these subjects in some way.\n\nBased on the user's taste, it is likely that they enjoy books that challenge them intellectually and emotionally, that offer complex and multi-dimensional characters and storylines, and that tackle important themes and social commentary in a thought-provoking way.", "favorite genre": ["the user seems to have a preference for fiction", "as most of the books listed fall under this category"], "favorite plot": ["the user seems to have a preference for complex", "multi-layered plots", "as many of the books listed feature intricate storylines with multiple subplots and character motivations"], "favorite setting": ["the user appears to enjoy a variety of settings", "ranging from fictional fantasy worlds to historical and maritime settings"], "favorite writing style": ["the user seems to appreciate a range of writing styles", "from the lyrical and descriptive prose of authors like tolstoy and james to the more straightforward and narrative-driven style of authors like stevenson and hemingway"], "favorite length": ["the user appears to have no preference for length", "as the list includes books of varying lengths", "from short novellas to longer epics"], "favorite topic": ["the user seems to have a particular interest in themes of love", "family", "and social commentary", "as many of the books listed tackle these subjects in some way"], "favorite pacing": ["the user appears to enjoy a range of pacing", "from the fast-paced action of \"a night to remember\" to the slower", "more introspective pacing of \"doctor zhivago"], "favorite narrative structure": ["the user appears to enjoy a variety of narrative structures", "from the linear and chronological structure of \"anna karenina\" to the more nonlinear and experimental structure of \"the master and margarita"], "favorite themes": ["the user appears to have a particular interest in themes of morality", "spirituality", "and the human condition", "as many of the books listed tackle these subjects in some way"]}