{"plain": "Based on the user's favourite books, it can be inferred that the user enjoys reading books that are:\nHumorous: The Real Frank Zappa Book and The Catcher in the Rye are both known for their comedic elements.\nRealistic: Goodbye, Columbus and Tortilla Flat are set in real-world locations and explore relatable themes.\nThought-provoking: From a Buick 8 explores philosophical and existential themes.\nWell-written: All of the books are praised for their writing style, which suggests the user has high standards for literary quality.\nVaried in length: The Real Frank Zappa Book is a short memoir, while From a Buick 8 is a longer novel, suggesting the user enjoys both shorter and longer reading experiences.\nIt can also be inferred that the user enjoys reading books that are:\nWell-crafted: All of the books are well-received and have a dedicated following, suggesting the user has good taste in literature.\nUnique: The Real Frank Zappa Book and From a Buick 8 are both unconventional in their subject matter and style, suggesting the user enjoys reading books that are outside the mainstream.\nIn conclusion, the user's taste in literature appears to be diverse and sophisticated, with a preference for well-crafted, humorous, realistic, and thought-provoking books that offer a unique reading experience.", "based on the user's favourite books, it can be inferred that the user enjoys reading books that are:\nhumorous": ["the real frank zappa book and the catcher in the rye are both known for their comedic elements"], "realistic": ["goodbye", "columbus and tortilla flat are set in real-world locations and explore relatable themes"], "thought-provoking": ["from a buick 8 explores philosophical and existential themes"], "well-written": ["all of the books are praised for their writing style", "which suggests the user has high standards for literary quality"], "varied in length": ["the real frank zappa book is a short memoir", "while from a buick 8 is a longer novel", "suggesting the user enjoys both shorter and longer reading experiences"], "it can also be inferred that the user enjoys reading books that are:\nwell-crafted": ["all of the books are well-received and have a dedicated following", "suggesting the user has good taste in literature"], "unique": ["the real frank zappa book and from a buick 8 are both unconventional in their subject matter and style", "suggesting the user enjoys reading books that are outside the mainstream"]}