{"plain": "Based on the user's favourite books, it can be inferred that the user enjoys reading books that are:\n- Fantasy/epic fiction: The Lions of Al-Rassan is a fantasy novel set in a fictional Middle Eastern-inspired world.\n- Mystery/thriller: The Curious Incident of the Dog in the Night-Time is a mystery novel that explores the themes of autism and child detective work.\n- Writing style: Both books are known for their unique writing styles, with The Lions of Al-Rassan being praised for its richly detailed world-building and The Curious Incident of the Dog in the Night-Time being praised for its innovative narrative structure and use of different fonts to represent different characters' thoughts.\n\nIt can also be inferred that the user enjoys reading books that are:\n- Well-written: Both books are highly regarded for their writing quality and have received critical acclaim.\n- Character-driven: Both books are known for their complex and well-developed characters, with The Lions of Al-Rassan exploring the themes of political intrigue, religion, and cultural identity, and The Curious Incident of the Dog in the Night-Time exploring the themes of autism, detective work, and family dynamics.\n\nIn summary, the user appears to have a broad range of interests when it comes to reading books, but seems to particularly enjoy books that are well-written, character-driven, and have a unique writing style.", "based on the user's favourite books, it can be inferred that the user enjoys reading books that are:\n- fantasy/epic fiction": ["the lions of al-rassan is a fantasy novel set in a fictional middle eastern-inspired world"], "- mystery/thriller": ["the curious incident of the dog in the night-time is a mystery novel that explores the themes of autism and child detective work"], "- writing style": ["both books are known for their unique writing styles", "with the lions of al-rassan being praised for its richly detailed world-building and the curious incident of the dog in the night-time being praised for its innovative narrative structure and use of different fonts to represent different characters' thoughts"], "it can also be inferred that the user enjoys reading books that are:\n- well-written": ["both books are highly regarded for their writing quality and have received critical acclaim"], "- character-driven": ["both books are known for their complex and well-developed characters", "with the lions of al-rassan exploring the themes of political intrigue", "religion", "and cultural identity", "and the curious incident of the dog in the night-time exploring the themes of autism", "detective work", "and family dynamics"]}