{"plain": "Based on the user's favourite books, it can be inferred that the user enjoys reading books that are:\n- Genre: Coming-of-age, dystopian, and fantasy.\n- Plot: Complex and thought-provoking.\n- Setting: Varied, including a high school, a remote island, and a parallel universe.\n- Writing Style: Stream-of-consciousness, poetic, and philosophical.\n- Length: Varies, from a novella to a trilogy.\n- Topic: Adolescence, society, and the nature of reality.\n- Pacing: Varied, with some parts being fast-paced and others being slower.\n- Narrative Structure: Non-linear, with flashbacks and jumps in time.\n- Themes: Coming-of-age, society, and the nature of reality.\n\nIt can also be inferred that the user enjoys reading books that challenge them and make them think deeply about complex topics. The user's taste seems to be for books that are well-crafted and have a strong sense of character development, world-building, and philosophical exploration. The user's favourite books also suggest a preference for books that are not afraid to tackle difficult subjects and explore them in a meaningful way.", "based on the user's favourite books, it can be inferred that the user enjoys reading books that are:\n- genre": ["coming-of-age", "dystopian", "and fantasy"], "- plot": ["complex and thought-provoking"], "- setting": ["varied", "including a high school", "a remote island", "and a parallel universe"], "- writing style": ["stream-of-consciousness", "poetic", "and philosophical"], "- length": ["varies", "from a novella to a trilogy"], "- topic": ["adolescence", "society", "and the nature of reality"], "- pacing": ["varied", "with some parts being fast-paced and others being slower"], "- narrative structure": ["non-linear", "with flashbacks and jumps in time"], "- themes": ["coming-of-age", "society", "and the nature of reality"]}