{"plain": "Based on the user's favourite books, it can be inferred that they enjoy reading books that are:\n- Fantasy/Alternate History: The Lions of Al-Rassan is set in a fictional alternate history of medieval Spain, while Hard-Boiled Wonderland and the End of the World is a fantasy novel.\n- Historical Fiction: The Lions of Al-Rassan is a historical fiction novel set in medieval Spain.\n- Literary Fiction: Foucault's Pendulum and The Unconsoled are both considered literary fiction novels.\n- Philosophical Fiction: Foucault's Pendulum explores themes of knowledge, power, and perception, while The Unconsoled delves into themes of morality and consciousness.\n\nIt can also be inferred that the user enjoys reading books that are:\n- Complex and Multi-Layered: All of the user's favourite books are complex and multi-layered, with intricate plots, well-developed characters, and multiple layers of meaning.\n- Thought-Provoking: All of the user's favourite books are thought-provoking, exploring deep and meaningful themes.\n\nBased on the user's favourite books, it can be inferred that they enjoy reading books that are:\n- Well-Written: All of the user's favourite books are well-written, with intricate and well-crafted prose.\n- Engaging: All of the user's favourite books are engaging, with compelling storylines and well-developed characters.\n\nBased on the user's favourite books, it can be inferred that they enjoy reading books that are:\n- Longer: All of the user's favourite books are longer, ranging from 400 to 600 pages.\n\nBased on the user's favourite books, it can be inferred that they enjoy reading books that are:\n- Richly Imagined: All of the user's favourite books are richly imagined, with well-crafted settings and intricate world-building.\n\nBased on the user's favourite books, it can be inferred that they enjoy reading books that are:\n- Paced Well: All of the user's favourite books are paced well, with a balance of action and introspection.\n\nBased on the user's favourite books, it can be inferred that they enjoy reading books that are:\n- Structured Well: All of the user's favourite books are structured well, with a clear narrative structure that enhances the reading experience.\n\nBased on the user's favourite books, it can be inferred that they enjoy reading books that explore:\n- Themes of Morality and Consciousness: The Unconsoled explores themes of morality and consciousness, while Foucault", "based on the user's favourite books, it can be inferred that they enjoy reading books that are:\n- fantasy/alternate history": ["the lions of al-rassan is set in a fictional alternate history of medieval spain", "while hard-boiled wonderland and the end of the world is a fantasy novel"], "- historical fiction": ["the lions of al-rassan is a historical fiction novel set in medieval spain"], "- literary fiction": ["foucault's pendulum and the unconsoled are both considered literary fiction novels"], "- philosophical fiction": ["foucault's pendulum explores themes of knowledge", "power", "and perception", "while the unconsoled delves into themes of morality and consciousness"], "it can also be inferred that the user enjoys reading books that are:\n- complex and multi-layered": ["all of the user's favourite books are complex and multi-layered", "with intricate plots", "well-developed characters", "and multiple layers of meaning"], "- thought-provoking": ["all of the user's favourite books are thought-provoking", "exploring deep and meaningful themes"], "based on the user's favourite books, it can be inferred that they enjoy reading books that are:\n- well-written": ["all of the user's favourite books are well-written", "with intricate and well-crafted prose"], "- engaging": ["all of the user's favourite books are engaging", "with compelling storylines and well-developed characters"], "based on the user's favourite books, it can be inferred that they enjoy reading books that are:\n- longer": ["all of the user's favourite books are longer", "ranging from 400 to 600 pages"], "based on the user's favourite books, it can be inferred that they enjoy reading books that are:\n- richly imagined": ["all of the user's favourite books are richly imagined", "with well-crafted settings and intricate world-building"], "based on the user's favourite books, it can be inferred that they enjoy reading books that are:\n- paced well": ["all of the user's favourite books are paced well", "with a balance of action and introspection"], "based on the user's favourite books, it can be inferred that they enjoy reading books that are:\n- structured well": ["all of the user's favourite books are structured well", "with a clear narrative structure that enhances the reading experience"], "based on the user's favourite books, it can be inferred that they enjoy reading books that explore:\n- themes of morality and consciousness": ["the unconsoled explores themes of morality and consciousness", "while foucault"]}