{"plain": "Based on the user's favourite books, it can be inferred that the user enjoys reading books that are:\n- Literary fiction: The Wind-Up Bird Chronicle and The Catcher in the Rye are examples of literary fiction that explore complex themes and characters.\n- Classic literature: The Plague is a classic novel that has been widely read and studied.\n- Coming-of-age stories: The Catcher in the Rye is a classic coming-of-age story that has been widely read and studied.\n- Philosophical fiction: The Plague explores themes of human nature, society, and the meaning of life.\n\nIt can also be inferred that the user enjoys reading books that are:\n- Character-driven: The Wind-Up Bird Chronicle and The Catcher in the Rye are examples of books that are driven by complex characters and their development.\n- Thought-provoking: The Plague and The Wind-Up Bird Chronicle explore complex themes and ideas that challenge the reader to think deeply.\n- Well-written: The user's favourite books are known for their well-crafted writing style and storytelling.\n\nIn terms of the user's favourite themes, it can be inferred that the user enjoys reading books that explore themes of:\n- Coming-of-age: The Catcher in the Rye is a classic coming-of-age story that explores the challenges and experiences of growing up.\n- Human nature: The Plague explores themes of human nature and the impact of society on individuals.\n- Philosophy: The Plague explores themes of the meaning of life and the nature of existence.\n- Identity: The Wind-Up Bird Chronicle explores themes of identity and the search for self.\n\nOverall, the user's taste in books suggests a preference for well-written, character-driven, and thought-provoking literary fiction that explores complex themes and ideas.", "based on the user's favourite books, it can be inferred that the user enjoys reading books that are:\n- literary fiction": ["the wind-up bird chronicle and the catcher in the rye are examples of literary fiction that explore complex themes and characters"], "- classic literature": ["the plague is a classic novel that has been widely read and studied"], "- coming-of-age stories": ["the catcher in the rye is a classic coming-of-age story that has been widely read and studied"], "- philosophical fiction": ["the plague explores themes of human nature", "society", "and the meaning of life"], "it can also be inferred that the user enjoys reading books that are:\n- character-driven": ["the wind-up bird chronicle and the catcher in the rye are examples of books that are driven by complex characters and their development"], "- thought-provoking": ["the plague and the wind-up bird chronicle explore complex themes and ideas that challenge the reader to think deeply"], "- well-written": ["the user's favourite books are known for their well-crafted writing style and storytelling"], "in terms of the user's favourite themes, it can be inferred that the user enjoys reading books that explore themes of:\n- coming-of-age": ["the catcher in the rye is a classic coming-of-age story that explores the challenges and experiences of growing up"], "- human nature": ["the plague explores themes of human nature and the impact of society on individuals"], "- philosophy": ["the plague explores themes of the meaning of life and the nature of existence"], "- identity": ["the wind-up bird chronicle explores themes of identity and the search for self"]}