{"plain": "Based on the list of favorite books provided, the following inferences can be made about the user's taste:\n\n1. Favorite genre: The user appears to have a preference for literary fiction, as evidenced by the inclusion of books such as \"The Sea, the Sea,\" \"The Human Stain,\" and \"Midnight's Children.\"\n\n2. Favorite plot: The user seems to enjoy complex, multi-layered plots, as seen in books like \"The Plot Against America\" and \"The Cement Garden.\"\n\n3. Favorite setting: The user appears to have a fondness for historical and cultural settings, as demonstrated by the presence of books set in different time periods and geographical locations, such as \"A Passage to India\" and \"Memoirs of Hadrian.\"\n\n4. Favorite writing style: The user seems to appreciate a more sophisticated, literary writing style, as seen in the inclusion of books like \"Dubliners\" and \"The Favourite Game.\"\n\n5. Favorite length: The user appears to have no preference for the length of books, as the list includes works of varying lengths, from short stories to novels.\n\n6. Favorite topic: The user seems to have an interest in exploring complex human themes, as evidenced by the presence of books that tackle issues such as identity, politics, and sexuality.\n\n7. Favorite pacing: The user appears to enjoy a balanced pacing, as seen in books that combine moments of tension and action with periods of reflection and introspection.\n\n8. Favorite narrative structure: The user seems to have a fondness for nonlinear narratives, as seen in books that employ non-chronological storytelling techniques.\n\n9. Favorite themes: The user appears to have an interest in exploring themes related to identity, politics, and sexuality, as seen in the inclusion of books such as \"The Human Stain\" and \"Lolita.\"\n\nIn summary, the user appears to have a well-rounded taste in literature, with a fondness for literary fiction, complex plots, historical and cultural settings, sophisticated writing styles, balanced pacing, nonlinear narratives, and themes related to identity, politics, and sexuality.", "favorite genre": ["the user appears to have a preference for literary fiction", "as evidenced by the inclusion of books such as \"the sea", "the sea,\" \"the human stain,\" and \"midnight's children"], "favorite plot": ["the user seems to enjoy complex", "multi-layered plots", "as seen in books like \"the plot against america\" and \"the cement garden"], "favorite setting": ["the user appears to have a fondness for historical and cultural settings", "as demonstrated by the presence of books set in different time periods and geographical locations", "such as \"a passage to india\" and \"memoirs of hadrian"], "favorite writing style": ["the user seems to appreciate a more sophisticated", "literary writing style", "as seen in the inclusion of books like \"dubliners\" and \"the favourite game"], "favorite length": ["the user appears to have no preference for the length of books", "as the list includes works of varying lengths", "from short stories to novels"], "favorite topic": ["the user seems to have an interest in exploring complex human themes", "as evidenced by the presence of books that tackle issues such as identity", "politics", "and sexuality"], "favorite pacing": ["the user appears to enjoy a balanced pacing", "as seen in books that combine moments of tension and action with periods of reflection and introspection"], "favorite narrative structure": ["the user seems to have a fondness for nonlinear narratives", "as seen in books that employ non-chronological storytelling techniques"], "favorite themes": ["the user appears to have an interest in exploring themes related to identity", "politics", "and sexuality", "as seen in the inclusion of books such as \"the human stain\" and \"lolita"]}