{"plain": "Based on the list of favorite books provided, the following can be inferred about the user's taste:\n\n1. Favorite genre: The user appears to have a preference for fiction, specifically coming-of-age stories, fantasy, and historical fiction.\n\n2. Favorite plot: The user seems to enjoy stories with a strong narrative arc, often involving character development and a journey of self-discovery.\n\n3. Favorite setting: The user seems to appreciate a variety of settings, ranging from historical Africa and medieval Europe to modern-day America and fictional worlds.\n\n4. Favorite writing style: The user appears to prefer a more literary and descriptive writing style, often with a focus on character development and emotional depth.\n\n5. Favorite length: The user seems to enjoy both shorter and longer works, ranging from novellas to full-length novels.\n\n6. Favorite topic: The user appears to have an interest in themes of love, friendship, family, and social justice, as well as the exploration of personal growth and identity.\n\n7. Favorite pacing: The user seems to enjoy a balance of action and introspection, with a steady pace that builds to a climax.\n\n8. Favorite narrative structure: The user appears to appreciate a variety of narrative structures, including linear, nonlinear, and episodic.\n\n9. Favorite themes: The user seems to enjoy stories that explore themes of faith, morality, and the human condition, as well as the celebration of community and the power of storytelling.\n\nBased on the user's taste, it is likely that they enjoy books that are rich in character development, emotional depth, and a compelling narrative. They may also appreciate books that tackle complex social issues and explore the human experience in a thoughtful and meaningful way.", "favorite genre": ["the user appears to have a preference for fiction", "specifically coming-of-age stories", "fantasy", "and historical fiction"], "favorite plot": ["the user seems to enjoy stories with a strong narrative arc", "often involving character development and a journey of self-discovery"], "favorite setting": ["the user seems to appreciate a variety of settings", "ranging from historical africa and medieval europe to modern-day america and fictional worlds"], "favorite writing style": ["the user appears to prefer a more literary and descriptive writing style", "often with a focus on character development and emotional depth"], "favorite length": ["the user seems to enjoy both shorter and longer works", "ranging from novellas to full-length novels"], "favorite topic": ["the user appears to have an interest in themes of love", "friendship", "family", "and social justice", "as well as the exploration of personal growth and identity"], "favorite pacing": ["the user seems to enjoy a balance of action and introspection", "with a steady pace that builds to a climax"], "favorite narrative structure": ["the user appears to appreciate a variety of narrative structures", "including linear", "nonlinear", "and episodic"], "favorite themes": ["the user seems to enjoy stories that explore themes of faith", "morality", "and the human condition", "as well as the celebration of community and the power of storytelling"]}