{"plain": "Based on the user's favourite books, it can be inferred that they enjoy:\nFantasy/Sci-Fi: The Neverending Story falls into both genres.\nAction/Thriller: Without Remorse is an action novel with thriller elements.\nPolitical Thriller: Executive Orders is a political thriller.\nIt can also be inferred that the user enjoys:\nComplex Plot: The Neverending Story has a complex plot involving multiple characters and timelines.\nRich Setting: The Neverending Story takes place in a richly imagined fantasy world.\nWell-Crafted Writing Style: All three books are well-crafted with strong writing styles.\nMedium Length: None of the books are overly long or short, suggesting a preference for medium-length novels.\nMature Topics: Without Remorse and Executive Orders deal with mature topics such as war, politics, and violence.\nPacing: The pacing of all three books is likely to be fast-paced and engaging.\nNarrative Structure: The Neverending Story uses a nonlinear narrative structure, suggesting a preference for unconventional storytelling.\nThemes: The Neverending Story explores themes of growing up, responsibility, and the power of stories.\nIn conclusion, the user enjoys complex, well-crafted fantasy, action, and political thrillers with mature topics, fast-paced pacing, and unconventional narrative structures that explore thought-provoking themes.", "based on the user's favourite books, it can be inferred that they enjoy:\nfantasy/sci-fi": ["the neverending story falls into both genres"], "action/thriller": ["without remorse is an action novel with thriller elements"], "political thriller": ["executive orders is a political thriller"], "it can also be inferred that the user enjoys:\ncomplex plot": ["the neverending story has a complex plot involving multiple characters and timelines"], "rich setting": ["the neverending story takes place in a richly imagined fantasy world"], "well-crafted writing style": ["all three books are well-crafted with strong writing styles"], "medium length": ["none of the books are overly long or short", "suggesting a preference for medium-length novels"], "mature topics": ["without remorse and executive orders deal with mature topics such as war", "politics", "and violence"], "pacing": ["the pacing of all three books is likely to be fast-paced and engaging"], "narrative structure": ["the neverending story uses a nonlinear narrative structure", "suggesting a preference for unconventional storytelling"], "themes": ["the neverending story explores themes of growing up", "responsibility", "and the power of stories"]}