{"plain": "Based on the user's favorite books, \"Myrren's Gift\" and \"Ender's Game,\" the following can be inferred about the user's taste:\n\n1. Favorite genre: Fantasy and Science Fiction.\n2. Favorite kind of plot: Complex and multi-layered, with a balance of action, adventure, and character development.\n3. Favorite setting: Imaginative and well-crafted worlds that are both familiar and alien.\n4. Favorite writing style: Vivid, descriptive, and with a strong sense of voice and perspective.\n5. Favorite length: Variable, but generally longer works that allow for a deeper exploration of characters and themes.\n6. Favorite topic: Exploration of the human condition, the nature of power and responsibility, and the search for meaning and purpose.\n7. Favorite pacing: A balance of fast-paced action and slower, more introspective moments that allow for character development and world-building.\n8. Favorite narrative structure: Non-linear, with flashbacks and multiple perspectives that add depth and complexity to the story.\n9. Favorite themes: The importance of community and teamwork, the dangers of blind obedience and conformity, and the struggle for personal growth and self-discovery.\n\nBased on these inferences, the user likely enjoys complex and well-crafted stories that blend elements of fantasy, science fiction, and human experience. They appreciate a balance of action, adventure, and character development, and enjoy being challenged by non-linear narratives and multiple perspectives. Their favorite books likely explore deep and meaningful themes, and are crafted with a strong sense of voice and perspective.", "favorite genre": ["fantasy and science fiction"], "favorite kind of plot": ["complex and multi-layered", "with a balance of action", "adventure", "and character development"], "favorite setting": ["imaginative and well-crafted worlds that are both familiar and alien"], "favorite writing style": ["vivid", "descriptive", "and with a strong sense of voice and perspective"], "favorite length": ["variable", "but generally longer works that allow for a deeper exploration of characters and themes"], "favorite topic": ["exploration of the human condition", "the nature of power and responsibility", "and the search for meaning and purpose"], "favorite pacing": ["a balance of fast-paced action and slower", "more introspective moments that allow for character development and world-building"], "favorite narrative structure": ["non-linear", "with flashbacks and multiple perspectives that add depth and complexity to the story"], "favorite themes": ["the importance of community and teamwork", "the dangers of blind obedience and conformity", "and the struggle for personal growth and self-discovery"]}