{"plain": "Based on the list of favorite books provided, the following can be inferred about the user's taste:\n\n1. Favorite genre: It can be inferred that the user enjoys reading a variety of genres, including historical fiction, mystery, science fiction, and non-fiction.\n\n2. Favorite plot: The user seems to enjoy complex plots with multiple layers and twists, as evidenced by the inclusion of books like \"The Name of the Rose\" and \"Foucault's Pendulum,\" which feature intricate storylines.\n\n3. Favorite setting: The user appears to have an interest in different historical periods and settings, as seen by the inclusion of books set in the past, such as \"The Man in the High Castle\" and \"A History of God.\"\n\n4. Favorite writing style: The user seems to appreciate well-crafted prose and a unique writing style, as evidenced by the inclusion of books like \"Foucault's Pendulum\" and \"Our Man in Havana,\" which feature distinct writing styles.\n\n5. Favorite length: It is not possible to infer the user's preference for book length based on the information provided.\n\n6. Favorite topic: The user seems to have an interest in a wide range of topics, including history, religion, espionage, and humor.\n\n7. Favorite pacing: The user appears to enjoy a balanced pacing, as evidenced by the inclusion of books with both fast-paced and slower-paced sections.\n\n8. Favorite narrative structure: The user seems to appreciate a variety of narrative structures, including linear, nonlinear, and multiple perspectives.\n\n9. Favorite themes: The user appears to enjoy exploring themes related to morality, identity, and the human condition, as evidenced by the inclusion of books like \"The Remains of the Day\" and \"Abduction!\"\n\nIn summary, the user appears to have a diverse and well-rounded taste in literature, enjoying books that offer a unique and engaging reading experience.", "favorite genre": ["it can be inferred that the user enjoys reading a variety of genres", "including historical fiction", "mystery", "science fiction", "and non-fiction"], "favorite plot": ["the user seems to enjoy complex plots with multiple layers and twists", "as evidenced by the inclusion of books like \"the name of the rose\" and \"foucault's pendulum,\" which feature intricate storylines"], "favorite setting": ["the user appears to have an interest in different historical periods and settings", "as seen by the inclusion of books set in the past", "such as \"the man in the high castle\" and \"a history of god"], "favorite writing style": ["the user seems to appreciate well-crafted prose and a unique writing style", "as evidenced by the inclusion of books like \"foucault's pendulum\" and \"our man in havana,\" which feature distinct writing styles"], "favorite length": ["it is not possible to infer the user's preference for book length based on the information provided"], "favorite topic": ["the user seems to have an interest in a wide range of topics", "including history", "religion", "espionage", "and humor"], "favorite pacing": ["the user appears to enjoy a balanced pacing", "as evidenced by the inclusion of books with both fast-paced and slower-paced sections"], "favorite narrative structure": ["the user seems to appreciate a variety of narrative structures", "including linear", "nonlinear", "and multiple perspectives"], "favorite themes": ["the user appears to enjoy exploring themes related to morality", "identity", "and the human condition", "as evidenced by the inclusion of books like \"the remains of the day\" and \"abduction!\"\n\nin summary", "the user appears to have a diverse and well-rounded taste in literature", "enjoying books that offer a unique and engaging reading experience"]}