{"plain": "Based on the user's favourite books, it can be inferred that the user enjoys:\n- Literary fiction: Both \"Ladder of Years\" and \"The Stone Diaries\" are considered literary fiction, known for their complex characters and themes.\n- Character-driven plots: Both books focus on the lives and experiences of their main characters, rather than relying on a traditional plot structure.\n- Multi-generational stories: Both books explore the lives and experiences of multiple generations, providing a rich and complex perspective on life.\n- Writing style: Both books are known for their rich and descriptive writing style, using language to create a vivid and immersive experience for the reader.\n- Length: Both books are considered to be of a reasonable length, not too short or too long, making them accessible and enjoyable for a wide range of readers.\n\nBased on the user's taste, it can be inferred that the user likely enjoys:\n- Thought-provoking themes: Both books are known for their exploration of complex and thought-provoking themes, such as family, identity, and the human experience.\n- Rich and complex characters: Both books are known for their well-developed and complex characters, who are explored in depth and provide a rich and immersive experience for the reader.\n- Multi-dimensional perspectives: Both books provide a multi-dimensional perspective on life, exploring the experiences and perspectives of multiple characters and generations.\n- Emotional resonance: Both books are known for their ability to resonate emotionally with readers, creating a powerful and immersive experience.\n\nIn summary, based on the user's favourite books, it can be inferred that the user enjoys literary fiction, character-driven plots, multi-generational stories, rich and descriptive writing style, and a reasonable length. Additionally, it can be inferred that the user likely enjoys thought-provoking themes, rich and complex characters, multi-dimensional perspectives, and emotional resonance.", "based on the user's favourite books, it can be inferred that the user enjoys:\n- literary fiction": ["both \"ladder of years\" and \"the stone diaries\" are considered literary fiction", "known for their complex characters and themes"], "- character-driven plots": ["both books focus on the lives and experiences of their main characters", "rather than relying on a traditional plot structure"], "- multi-generational stories": ["both books explore the lives and experiences of multiple generations", "providing a rich and complex perspective on life"], "- writing style": ["both books are known for their rich and descriptive writing style", "using language to create a vivid and immersive experience for the reader"], "- length": ["both books are considered to be of a reasonable length", "not too short or too long", "making them accessible and enjoyable for a wide range of readers"], "based on the user's taste, it can be inferred that the user likely enjoys:\n- thought-provoking themes": ["both books are known for their exploration of complex and thought-provoking themes", "such as family", "identity", "and the human experience"], "- rich and complex characters": ["both books are known for their well-developed and complex characters", "who are explored in depth and provide a rich and immersive experience for the reader"], "- multi-dimensional perspectives": ["both books provide a multi-dimensional perspective on life", "exploring the experiences and perspectives of multiple characters and generations"], "- emotional resonance": ["both books are known for their ability to resonate emotionally with readers", "creating a powerful and immersive experience"]}