{"plain": "Based on the list of favorite books provided, the following inferences can be made about the user's taste:\n\n1. Favorite genre: The user appears to have a preference for dystopian and anti-war fiction, as well as philosophical and literary works.\n\n2. Favorite plot: The user seems to enjoy complex and thought-provoking plots, often involving social commentary and exploration of human nature.\n\n3. Favorite setting: The user seems to have a preference for historical and fictional settings, ranging from wartime Europe to alternative American histories.\n\n4. Favorite writing style: The user appears to appreciate a variety of writing styles, from the stream-of-consciousness of philosophical investigations to the more traditional narrative structure of novels.\n\n5. Favorite length: The user seems to have no preference for the length of the books they read, as the list includes both short philosophical works and longer novels.\n\n6. Favorite topic: The user appears to have an interest in a wide range of topics, from political commentary to philosophical exploration to historical fiction.\n\n7. Favorite pacing: The user seems to enjoy a range of pacing styles, from the slow and introspective to the fast-paced and action-packed.\n\n8. Favorite narrative structure: The user appears to have a preference for nonlinear and experimental narrative structures, often involving multiple perspectives and nonlinear timelines.\n\n9. Favorite themes: The user appears to have an interest in themes related to social commentary, political critique, philosophical exploration, and human nature.\n\nOverall, the user appears to have a diverse and well-rounded taste in literature, enjoying works that challenge their assumptions and explore complex themes through a variety of narrative structures and writing styles.", "favorite genre": ["the user appears to have a preference for dystopian and anti-war fiction", "as well as philosophical and literary works"], "favorite plot": ["the user seems to enjoy complex and thought-provoking plots", "often involving social commentary and exploration of human nature"], "favorite setting": ["the user seems to have a preference for historical and fictional settings", "ranging from wartime europe to alternative american histories"], "favorite writing style": ["the user appears to appreciate a variety of writing styles", "from the stream-of-consciousness of philosophical investigations to the more traditional narrative structure of novels"], "favorite length": ["the user seems to have no preference for the length of the books they read", "as the list includes both short philosophical works and longer novels"], "favorite topic": ["the user appears to have an interest in a wide range of topics", "from political commentary to philosophical exploration to historical fiction"], "favorite pacing": ["the user seems to enjoy a range of pacing styles", "from the slow and introspective to the fast-paced and action-packed"], "favorite narrative structure": ["the user appears to have a preference for nonlinear and experimental narrative structures", "often involving multiple perspectives and nonlinear timelines"], "favorite themes": ["the user appears to have an interest in themes related to social commentary", "political critique", "philosophical exploration", "and human nature"]}