{"plain": "Based on the user's favourite books, it can be inferred that the user enjoys:\nFantasy: \"Angel Fire East\" is a fantasy novel.\nPost-Apocalyptic Fiction: \"The Brief History of the Dead\" is a post-apocalyptic novel.\nCreative and Imaginative Writing: Both books are known for their creative and imaginative storytelling.\nCompelling Narratives: Both books have been praised for their compelling narratives.\nThought-Provoking Themes: Both books explore thought-provoking themes such as life, death, and the nature of reality.\nIn conclusion, the user appears to have a taste for imaginative, thought-provoking fiction with compelling narratives.", "based on the user's favourite books, it can be inferred that the user enjoys:\nfantasy": ["\"angel fire east\" is a fantasy novel"], "post-apocalyptic fiction": ["\"the brief history of the dead\" is a post-apocalyptic novel"], "creative and imaginative writing": ["both books are known for their creative and imaginative storytelling"], "compelling narratives": ["both books have been praised for their compelling narratives"], "thought-provoking themes": ["both books explore thought-provoking themes such as life", "death", "and the nature of reality"]}