{"plain": "Based on the user's favourite books, it can be inferred that the user enjoys:\nFantasy fiction: The Mists of Avalon and The Summer Tree are set in mythical times and places.\nAlternate history fiction: The Mists of Avalon is a retelling of the King Arthur legend from a feminist perspective, while The Fifth Sacred Thing is a speculative fiction set in an alternate version of San Francisco.\nRomance fiction: An Assembly Such as This is a Regency romance novel.\nEpistolary fiction: An Assembly Such as This is written in the form of letters and journal entries.\nNovellas: The Summer Tree is a novella, which is a shorter form of a novel.\nFeminist fiction: The Mists of Avalon and The Fifth Sacred Thing both explore feminist themes and perspectives.\nMulti-POV narrative: The Mists of Avalon and The Fifth Sacred Thing both feature multiple points of view, allowing the reader to experience the story from different characters' perspectives.\nIt can also be inferred that the user enjoys:\nHistorical fiction: The Mists of Avalon is set in a fictional version of the Dark Ages, while An Assembly Such as This is set in Regency England.\nMythology: The Mists of Avalon is based on the King Arthur legend, and The Summer Tree is set in a mythical world inspired by Celtic mythology.\nSpeculative fiction: The Fifth Sacred Thing is a speculative fiction that explores an alternate version of San Francisco.\nDiversity and inclusion: The Fifth Sacred Thing explores themes of diversity and inclusion, and The Mists of Avalon features a diverse cast of characters.\nCharacter-driven stories: The Mists of Avalon, The Fifth Sacred Thing, and An Assembly Such as This are all character-driven stories that focus on the development and relationships of the characters.\nBased on the user's favourite books, it can be inferred that the user enjoys:\nFantasy fiction: The Mists of Avalon and The Summer Tree are set in mythical times and places.\nAlternate history fiction: The Mists of Avalon is a retelling of the King Arthur legend from a feminist perspective, while The Fifth Sacred Thing is a speculative fiction set in an alternate version of San Francisco.\nRomance fiction: An Assembly Such as This is a Regency romance novel.\nEpistolary fiction: An Assembly Such as This is written in the form of letters and journal entries.\nNovellas: The Summer Tree is a novella, which is a shorter form of a novel.\nFeminist fiction: The Mists of Aval", "based on the user's favourite books, it can be inferred that the user enjoys:\nfantasy fiction": ["the mists of avalon and the summer tree are set in mythical times and places"], "alternate history fiction": ["the mists of avalon is a retelling of the king arthur legend from a feminist perspective", "while the fifth sacred thing is a speculative fiction set in an alternate version of san francisco"], "romance fiction": ["an assembly such as this is a regency romance novel"], "epistolary fiction": ["an assembly such as this is written in the form of letters and journal entries"], "novellas": ["the summer tree is a novella", "which is a shorter form of a novel"], "feminist fiction": ["the mists of aval"], "multi-pov narrative": ["the mists of avalon and the fifth sacred thing both feature multiple points of view", "allowing the reader to experience the story from different characters' perspectives"], "it can also be inferred that the user enjoys:\nhistorical fiction": ["the mists of avalon is set in a fictional version of the dark ages", "while an assembly such as this is set in regency england"], "mythology": ["the mists of avalon is based on the king arthur legend", "and the summer tree is set in a mythical world inspired by celtic mythology"], "speculative fiction": ["the fifth sacred thing is a speculative fiction that explores an alternate version of san francisco"], "diversity and inclusion": ["the fifth sacred thing explores themes of diversity and inclusion", "and the mists of avalon features a diverse cast of characters"], "character-driven stories": ["the mists of avalon", "the fifth sacred thing", "and an assembly such as this are all character-driven stories that focus on the development and relationships of the characters"]}