{"plain": "Based on the user's favorite books, it can be inferred that they enjoy reading books that are:\n- Non-fiction: All of the books mentioned are non-fiction, with a focus on topics such as shamanism, memory, philosophy, and literature.\n- Academic: All of the books mentioned are written by academics or scholars in their respective fields.\n- Dense: All of the books mentioned are dense, with a lot of information and ideas packed into them.\n\nIt can also be inferred that the user enjoys reading books that are:\n- Thought-provoking: All of the books mentioned are likely to challenge the reader's assumptions and perspectives, and encourage them to think deeply about the topics covered.\n- Well-researched: All of the books mentioned are likely to be well-researched and based on extensive research and scholarship.\n- Complex: All of the books mentioned are likely to be complex, with multiple layers of meaning and interpretation.\n\nIn terms of specific themes, it can be inferred that the user enjoys reading books that explore:\n- Memory and the nature of human memory\n- The history and practice of shamanism\n- The nature of language and meaning\n- The impact of war and destruction on society and culture\n- The history and development of literature and writing.\n\nOverall, it can be inferred that the user has a deep appreciation for non-fiction, academic, dense, thought-provoking, well-researched, and complex books that explore a wide range of themes and topics.", "based on the user's favorite books, it can be inferred that they enjoy reading books that are:\n- non-fiction": ["all of the books mentioned are non-fiction", "with a focus on topics such as shamanism", "memory", "philosophy", "and literature"], "- academic": ["all of the books mentioned are written by academics or scholars in their respective fields"], "- dense": ["all of the books mentioned are dense", "with a lot of information and ideas packed into them"], "it can also be inferred that the user enjoys reading books that are:\n- thought-provoking": ["all of the books mentioned are likely to challenge the reader's assumptions and perspectives", "and encourage them to think deeply about the topics covered"], "- well-researched": ["all of the books mentioned are likely to be well-researched and based on extensive research and scholarship"], "- complex": ["all of the books mentioned are likely to be complex", "with multiple layers of meaning and interpretation"]}