{"plain": "Based on the user's favourite books, it can be inferred that the user enjoys:\nFantasy: Good Omens is a fantasy novel.\nHumor: Both Good Omens and The Fifth Elephant contain humorous elements.\nTongue-in-Cheek Satire: Good Omens is a tongue-in-cheek satire of religion and good and evil.\nBritish Humor: The Fifth Elephant is a mystery novel with a British humor.\nDiverse Settings: The Fifth Elephant takes place in Victorian London, while Good Omens is set in a fictional town in England.\nComplex Plot: Both The Fifth Elephant and Good Omens have complex plots with multiple subplots and twists.\nWell-developed Characters: The Fifth Elephant and Good Omens both have well-developed characters that are memorable and relatable.\nIn conclusion, the user's taste in literature seems to be diverse, with a preference for humorous, tongue-in-cheek satire and complex plots with well-developed characters.", "based on the user's favourite books, it can be inferred that the user enjoys:\nfantasy": ["good omens is a fantasy novel"], "humor": ["both good omens and the fifth elephant contain humorous elements"], "tongue-in-cheek satire": ["good omens is a tongue-in-cheek satire of religion and good and evil"], "british humor": ["the fifth elephant is a mystery novel with a british humor"], "diverse settings": ["the fifth elephant takes place in victorian london", "while good omens is set in a fictional town in england"], "complex plot": ["both the fifth elephant and good omens have complex plots with multiple subplots and twists"], "well-developed characters": ["the fifth elephant and good omens both have well-developed characters that are memorable and relatable"]}