{"plain": "Based on the list of favorite books provided, the following inferences can be made about the user's taste:\n\n1. Favorite genre: The user seems to have a preference for fiction, as well as non-fiction books related to history, politics, and social issues.\n\n2. Favorite plot: The user appears to enjoy complex, multi-layered plots with a focus on character development and social commentary.\n\n3. Favorite setting: The user seems to have a preference for books set in historical or contemporary contexts, with a focus on human experiences and social commentary.\n\n4. Favorite writing style: The user seems to appreciate a variety of writing styles, from literary to more straightforward, as long as the writing is engaging and thought-provoking.\n\n5. Favorite length: The user seems to have no preference for book length, as the list includes books of various lengths.\n\n6. Favorite topic: The user appears to have an interest in a wide range of topics, from historical events to social issues to fiction.\n\n7. Favorite pacing: The user seems to enjoy a balance of action and reflection in their reading, as the list includes books with different pacing styles.\n\n8. Favorite narrative structure: The user seems to appreciate a variety of narrative structures, from linear to non-linear, as long as the story is engaging and thought-provoking.\n\n9. Favorite themes: The user appears to have an interest in themes related to social commentary, human experiences, and historical events.\n\nBased on the list of favorite books provided, the following inferences can be made about the user's taste:\n\n1. Favorite genre: The user seems to have a preference for fiction, as well as non-fiction books related to history, politics, and social issues.\n\n2. Favorite plot: The user appears to enjoy complex, multi-layered plots with a focus on character development and social commentary.\n\n3. Favorite setting: The user seems to have a preference for books set in historical or contemporary contexts, with a focus on human experiences and social commentary.\n\n4. Favorite writing style: The user seems to appreciate a variety of writing styles, from literary to more straightforward, as long as the writing is engaging and thought-provoking.\n\n5. Favorite length: The user seems to have no preference for book length, as the list includes books of various lengths.\n\n6. Favorite topic: The user appears to have an interest in a wide range of topics, from historical events to social issues to fiction.\n\n7. Favorite pacing: The user seems to enjoy a balance of action and reflection in their reading, as the", "favorite genre": ["the user seems to have a preference for fiction", "as well as non-fiction books related to history", "politics", "and social issues"], "favorite plot": ["the user appears to enjoy complex", "multi-layered plots with a focus on character development and social commentary"], "favorite setting": ["the user seems to have a preference for books set in historical or contemporary contexts", "with a focus on human experiences and social commentary"], "favorite writing style": ["the user seems to appreciate a variety of writing styles", "from literary to more straightforward", "as long as the writing is engaging and thought-provoking"], "favorite length": ["the user seems to have no preference for book length", "as the list includes books of various lengths"], "favorite topic": ["the user appears to have an interest in a wide range of topics", "from historical events to social issues to fiction"], "favorite pacing": ["the user seems to enjoy a balance of action and reflection in their reading", "as the"], "favorite narrative structure": ["the user seems to appreciate a variety of narrative structures", "from linear to non-linear", "as long as the story is engaging and thought-provoking"], "favorite themes": ["the user appears to have an interest in themes related to social commentary", "human experiences", "and historical events"]}