{"plain": "Based on the user's favourite books, it can be inferred that the user enjoys reading books with a mix of the following features:\n\nGenre: Literary fiction, dystopian, and historical fiction.\nPlot: Complex, multi-layered, and thought-provoking.\nSetting: Varied, ranging from historical to contemporary, and from fictional to real-world locations.\nWriting Style: Stream-of-consciousness, first-person narration, and vivid descriptions.\nLength: Varies, from short stories to full-length novels.\nTopic: Social commentary, human nature, and coming-of-age stories.\nPacing: Slow-burn, with a focus on character development and world-building.\nNarrative Structure: Non-linear, with flashbacks and jumps in time.\nThemes: Morality, identity, and the human condition.\n\nIt can also be inferred that the user enjoys reading books that challenge their perceptions and explore complex themes through well-crafted storytelling. The user's taste seems to be diverse, as they enjoy books with different settings, writing styles, and topics. The user's preference for literary fiction and dystopian novels suggests a fondness for speculative fiction and a willingness to engage with difficult subjects. The user's appreciation for historical fiction and books set in real-world locations indicates a desire for authenticity and a connection to the past. The user's enjoyment of complex narrative structures and non-linear storytelling suggests a fondness for experimentation and a willingness to be challenged by unconventional storytelling techniques. Overall, the user's taste appears to be sophisticated and well-informed, with a deep appreciation for the power of literature to explore complex themes and challenge perceptions.", "based on the user's favourite books, it can be inferred that the user enjoys reading books with a mix of the following features:\n\ngenre": ["literary fiction", "dystopian", "and historical fiction"], "plot": ["complex", "multi-layered", "and thought-provoking"], "setting": ["varied", "ranging from historical to contemporary", "and from fictional to real-world locations"], "writing style": ["stream-of-consciousness", "first-person narration", "and vivid descriptions"], "length": ["varies", "from short stories to full-length novels"], "topic": ["social commentary", "human nature", "and coming-of-age stories"], "pacing": ["slow-burn", "with a focus on character development and world-building"], "narrative structure": ["non-linear", "with flashbacks and jumps in time"], "themes": ["morality", "identity", "and the human condition"]}