{"plain": "Based on the user's favorite books, it can be inferred that they enjoy reading books that are:\n- Children's literature: \"A Little Princess\" is a classic children's book.\n- Historical fiction: \"Sophie's World\" is a novel that explores the history of philosophy and ideas.\n- Fantasy: \"A Little Princess\" has elements of fantasy and imagination.\n\nIn terms of writing style, the user likely enjoys books that are:\n- Well-written: Both \"A Little Princess\" and \"Sophie's World\" are highly regarded for their writing style and storytelling.\n- Engaging: The user's choice of books suggests they enjoy reading stories that are engaging and immersive.\n\nIn terms of themes, the user likely enjoys books that explore:\n- Empathy: \"A Little Princess\" explores themes of empathy and compassion.\n- Self-discovery: \"Sophie's World\" delves into themes of self-discovery and the search for meaning.\n\nOverall, the user's taste in books suggests they enjoy reading stories that are imaginative, well-written, and explore themes of empathy, self-discovery, and the search for meaning.", "based on the user's favorite books, it can be inferred that they enjoy reading books that are:\n- children's literature": ["\"a little princess\" is a classic children's book"], "- historical fiction": ["\"sophie's world\" is a novel that explores the history of philosophy and ideas"], "- fantasy": ["\"a little princess\" has elements of fantasy and imagination"], "in terms of writing style, the user likely enjoys books that are:\n- well-written": ["both \"a little princess\" and \"sophie's world\" are highly regarded for their writing style and storytelling"], "- engaging": ["the user's choice of books suggests they enjoy reading stories that are engaging and immersive"], "in terms of themes, the user likely enjoys books that explore:\n- empathy": ["\"a little princess\" explores themes of empathy and compassion"], "- self-discovery": ["\"sophie's world\" delves into themes of self-discovery and the search for meaning"]}