{"plain": "Based on the user's favourite books, it can be inferred that the user enjoys:\nFantasy: Both \"Across the Nightingale Floor\" and \"Another Fine Myth\" fall into this genre.\nAsian-inspired settings: \"Snow Flower and the Secret Fan\" is set in 19th century China, and \"Across the Nightingale Floor\" is set in feudal Japan.\nStrong female characters: \"Snow Flower and the Secret Fan\" features a strong female protagonist, and \"Another Fine Myth\" also has a prominent female character.\nHumor: \"Another Fine Myth\" has elements of humor throughout the story.\nMagic: Both \"Another Fine Myth\" and \"Across the Nightingale Floor\" feature magic as a central theme.\nLush descriptions: The user likely enjoys richly described settings and characters, as both \"Snow Flower and the Secret Fan\" and \"Across the Nightingale Floor\" are known for their vivid writing.\nEpistolary format: \"Snow Flower and the Secret Fan\" is written in the form of letters and poems, which the user likely finds engaging.\nRichly developed world-building: Both \"Across the Nightingale Floor\" and \"Another Fine Myth\" feature well-crafted fictional worlds that the user finds immersive.\nIntricate plot: All three books feature complex and intricate plots that keep the reader engaged.\nThemes of friendship and family: \"Another Fine Myth\" explores themes of friendship and family, and \"Snow Flower and the Secret Fan\" also touches on these themes.\nBased on the user's preferences, it can be inferred that the user likely enjoys:\nLonger books: All three of the user's favourite books are of novel length, suggesting a preference for longer works.\nRichly developed characters: The user likely enjoys well-crafted, complex characters that are fully realized and multi-dimensional.\nSlow-burn pacing: The user likely enjoys stories that unfold at a slower pace, allowing for deeper immersion and character development.\nHistorical fiction: \"Snow Flower and the Secret Fan\" is a historical fiction, and the user likely enjoys this genre.\nFantasy of manners: \"Another Fine Myth\" is a fantasy of manners, and the user likely enjoys this sub-genre of fantasy.\nMagic systems with depth: Both \"Another Fine Myth\" and \"Across the Nightingale Floor\" feature well-crafted magic systems that are integral to the story and have depth of lore.\nStrong themes of identity and belonging: \"Across the Nightingale Floor\" explores themes of identity and belonging, and the user likely finds these themes", "based on the user's favourite books, it can be inferred that the user enjoys:\nfantasy": ["both \"across the nightingale floor\" and \"another fine myth\" fall into this genre"], "asian-inspired settings": ["\"snow flower and the secret fan\" is set in 19th century china", "and \"across the nightingale floor\" is set in feudal japan"], "strong female characters": ["\"snow flower and the secret fan\" features a strong female protagonist", "and \"another fine myth\" also has a prominent female character"], "humor": ["\"another fine myth\" has elements of humor throughout the story"], "magic": ["both \"another fine myth\" and \"across the nightingale floor\" feature magic as a central theme"], "lush descriptions": ["the user likely enjoys richly described settings and characters", "as both \"snow flower and the secret fan\" and \"across the nightingale floor\" are known for their vivid writing"], "epistolary format": ["\"snow flower and the secret fan\" is written in the form of letters and poems", "which the user likely finds engaging"], "richly developed world-building": ["both \"across the nightingale floor\" and \"another fine myth\" feature well-crafted fictional worlds that the user finds immersive"], "intricate plot": ["all three books feature complex and intricate plots that keep the reader engaged"], "themes of friendship and family": ["\"another fine myth\" explores themes of friendship and family", "and \"snow flower and the secret fan\" also touches on these themes"], "based on the user's preferences, it can be inferred that the user likely enjoys:\nlonger books": ["all three of the user's favourite books are of novel length", "suggesting a preference for longer works"], "richly developed characters": ["the user likely enjoys well-crafted", "complex characters that are fully realized and multi-dimensional"], "slow-burn pacing": ["the user likely enjoys stories that unfold at a slower pace", "allowing for deeper immersion and character development"], "historical fiction": ["\"snow flower and the secret fan\" is a historical fiction", "and the user likely enjoys this genre"], "fantasy of manners": ["\"another fine myth\" is a fantasy of manners", "and the user likely enjoys this sub-genre of fantasy"], "magic systems with depth": ["both \"another fine myth\" and \"across the nightingale floor\" feature well-crafted magic systems that are integral to the story and have depth of lore"], "strong themes of identity and belonging": ["\"across the nightingale floor\" explores themes of identity and belonging", "and the user likely finds these themes"]}