{"plain": "Based on the user's favourite books, it can be inferred that they enjoy reading books with the following features:\n\nGenre: The user seems to have a preference for literary fiction, as all of the books mentioned are considered to be in this genre.\n\nPlot: The user appears to enjoy complex and multi-layered plots, as all of the books mentioned have intricate storylines.\n\nSetting: The user seems to have a fondness for books set in different times and places, as all of the books mentioned are set in various historical periods and geographical locations.\n\nWriting Style: The user appears to appreciate a more lyrical and descriptive writing style, as all of the books mentioned are known for their rich and evocative language.\n\nLength: The user seems to have no preference for the length of the books they read, as all of the books mentioned vary in length.\n\nTopic: The user appears to have an interest in books that explore a wide range of topics, as all of the books mentioned have different themes and subjects.\n\nPacing: The user seems to enjoy books with a slow and contemplative pacing, as all of the books mentioned are known for their leisurely and reflective tone.\n\nNarrative Structure: The user appears to appreciate a nonlinear narrative structure, as all of the books mentioned use non-traditional storytelling techniques.\n\nThemes: The user seems to have a fondness for books that explore themes of identity, memory, and the human condition.\n\nBased on the user's preferences, it is likely that they enjoy reading books that are thought-provoking, emotionally resonant, and richly imagined. They may also have an appreciation for books that challenge traditional narrative conventions and offer a unique and immersive reading experience.", "based on the user's favourite books, it can be inferred that they enjoy reading books with the following features:\n\ngenre": ["the user seems to have a preference for literary fiction", "as all of the books mentioned are considered to be in this genre"], "plot": ["the user appears to enjoy complex and multi-layered plots", "as all of the books mentioned have intricate storylines"], "setting": ["the user seems to have a fondness for books set in different times and places", "as all of the books mentioned are set in various historical periods and geographical locations"], "writing style": ["the user appears to appreciate a more lyrical and descriptive writing style", "as all of the books mentioned are known for their rich and evocative language"], "length": ["the user seems to have no preference for the length of the books they read", "as all of the books mentioned vary in length"], "topic": ["the user appears to have an interest in books that explore a wide range of topics", "as all of the books mentioned have different themes and subjects"], "pacing": ["the user seems to enjoy books with a slow and contemplative pacing", "as all of the books mentioned are known for their leisurely and reflective tone"], "narrative structure": ["the user appears to appreciate a nonlinear narrative structure", "as all of the books mentioned use non-traditional storytelling techniques"], "themes": ["the user seems to have a fondness for books that explore themes of identity", "memory", "and the human condition"]}