{"plain": "Based on the list of favorite books provided, the following can be inferred about the user's taste:\n\n1. Favorite genre: It can be inferred that the user enjoys reading a variety of genres, including mystery (Death on the Nile), classic literature (Pride and Prejudice), science fiction (Barrayar, Komarr, The Witches of Karres, The Heritage of Hastur), and young adult fiction (The Curious Incident of the Dog in the Night-Time).\n\n2. Favorite plot: The user seems to enjoy complex plots with multiple subplots and character development, as evidenced by the choice of books with intricate storylines.\n\n3. Favorite setting: The user appears to have a preference for historical settings, as seen in The Eagle Has Landed and Death on the Nile, as well as fictional worlds, such as those in science fiction novels.\n\n4. Favorite writing style: The user seems to appreciate a variety of writing styles, from the classic literature of Pride and Prejudice to the more modern style of The Curious Incident of the Dog in the Night-Time.\n\n5. Favorite length: The user's preference for longer books suggests a taste for more complex and detailed stories.\n\n6. Favorite topic: The user's interest in a wide range of topics, from mystery and classic literature to science fiction and young adult fiction, suggests a broad range of interests and a willingness to explore new ideas and themes.\n\n7. Favorite pacing: The user seems to enjoy a steady pace with occasional moments of tension and suspense, as evidenced by the choice of books with a balance of action and character development.\n\n8. Favorite narrative structure: The user appears to prefer a traditional narrative structure, with a clear beginning, middle, and end, as seen in the choice of books with a clear plot and character development.\n\n9. Favorite themes: The user seems to enjoy books that explore a variety of themes, including social justice (To Kill a Mockingbird), war (The Longest Day), and the human condition (The Quiet American, The Shattered Chain, A Civil Campaign).\n\nIn summary, the user appears to have a diverse and well-rounded taste in literature, enjoying books that offer complex plots, detailed settings, and a range of themes and writing styles.", "favorite genre": ["it can be inferred that the user enjoys reading a variety of genres", "including mystery (death on the nile)", "classic literature (pride and prejudice)", "science fiction (barrayar", "komarr", "the witches of karres", "the heritage of hastur)", "and young adult fiction (the curious incident of the dog in the night-time)"], "favorite plot": ["the user seems to enjoy complex plots with multiple subplots and character development", "as evidenced by the choice of books with intricate storylines"], "favorite setting": ["the user appears to have a preference for historical settings", "as seen in the eagle has landed and death on the nile", "as well as fictional worlds", "such as those in science fiction novels"], "favorite writing style": ["the user seems to appreciate a variety of writing styles", "from the classic literature of pride and prejudice to the more modern style of the curious incident of the dog in the night-time"], "favorite length": ["the user's preference for longer books suggests a taste for more complex and detailed stories"], "favorite topic": ["the user's interest in a wide range of topics", "from mystery and classic literature to science fiction and young adult fiction", "suggests a broad range of interests and a willingness to explore new ideas and themes"], "favorite pacing": ["the user seems to enjoy a steady pace with occasional moments of tension and suspense", "as evidenced by the choice of books with a balance of action and character development"], "favorite narrative structure": ["the user appears to prefer a traditional narrative structure", "with a clear beginning", "middle", "and end", "as seen in the choice of books with a clear plot and character development"], "favorite themes": ["the user seems to enjoy books that explore a variety of themes", "including social justice (to kill a mockingbird)", "war (the longest day)", "and the human condition (the quiet american", "the shattered chain", "a civil campaign)"]}