{"plain": "Based on the user's favourite books, it can be inferred that the user enjoys reading books that are:\n- Plot-driven: All three books have intricate and engaging storylines that keep the reader hooked.\n- Character-driven: All three books have well-developed and complex characters that the reader can relate to and root for.\n- Realistic: All three books are set in real-world locations and deal with relatable themes and issues.\n- Thought-provoking: All three books make the reader question their assumptions and explore complex moral and ethical issues.\n- Well-written: All three books are praised for their excellent writing style, dialogue, and prose.\n\nIt can also be inferred that the user enjoys reading books that are:\n- Lengthy: All three books are considered to be \"long\" by some readers, indicating that the user may prefer longer books over shorter ones.\n- Complex: All three books are considered to be \"complex\" by some readers, indicating that the user may prefer books that are challenging and require deeper thought and analysis.\n\nBased on the user's favourite books, it can be inferred that the user enjoys reading books that are:\n- Well-researched: All three books are praised for their accuracy and attention to detail, suggesting that the user may prefer books that are well-researched and based on real-world events and issues.\n- Engaging: All three books are praised for their ability to keep the reader engaged and interested throughout the entire story.\n- Emotional: All three books are praised for their ability to evoke strong emotions and feelings in the reader, suggesting that the user may prefer books that are emotionally impactful.\n\nBased on the user's favourite books, it can be inferred that the user enjoys reading books that are:\n- Challenging: All three books are considered to be \"challenging\" by some readers, indicating that the user may prefer books that are intellectually stimulating and require deeper thought and analysis.\n- Multilayered: All three books are praised for their complexity and depth, suggesting that the user may prefer books that are multilayered and have multiple themes and issues explored throughout the story.\n\nBased on the user's favourite books, it can be inferred that the user enjoys reading books that are:\n- Well-written: All three books are praised for their excellent writing style, dialogue, and prose, suggesting that the user may prefer books that are well-written and crafted with care and attention to detail.\n- Memorable: All three books are praised for their ability to stay with the reader long after the story is finished,", "based on the user's favourite books, it can be inferred that the user enjoys reading books that are:\n- plot-driven": ["all three books have intricate and engaging storylines that keep the reader hooked"], "- character-driven": ["all three books have well-developed and complex characters that the reader can relate to and root for"], "- realistic": ["all three books are set in real-world locations and deal with relatable themes and issues"], "- thought-provoking": ["all three books make the reader question their assumptions and explore complex moral and ethical issues"], "- well-written": ["all three books are praised for their excellent writing style", "dialogue", "and prose"], "it can also be inferred that the user enjoys reading books that are:\n- lengthy": ["all three books are considered to be \"long\" by some readers", "indicating that the user may prefer longer books over shorter ones"], "- complex": ["all three books are considered to be \"complex\" by some readers", "indicating that the user may prefer books that are challenging and require deeper thought and analysis"], "based on the user's favourite books, it can be inferred that the user enjoys reading books that are:\n- well-researched": ["all three books are praised for their accuracy and attention to detail", "suggesting that the user may prefer books that are well-researched and based on real-world events and issues"], "- engaging": ["all three books are praised for their ability to keep the reader engaged and interested throughout the entire story"], "- emotional": ["all three books are praised for their ability to evoke strong emotions and feelings in the reader", "suggesting that the user may prefer books that are emotionally impactful"], "based on the user's favourite books, it can be inferred that the user enjoys reading books that are:\n- challenging": ["all three books are considered to be \"challenging\" by some readers", "indicating that the user may prefer books that are intellectually stimulating and require deeper thought and analysis"], "- multilayered": ["all three books are praised for their complexity and depth", "suggesting that the user may prefer books that are multilayered and have multiple themes and issues explored throughout the story"], "based on the user's favourite books, it can be inferred that the user enjoys reading books that are:\n- well-written": ["all three books are praised for their excellent writing style", "dialogue", "and prose", "suggesting that the user may prefer books that are well-written and crafted with care and attention to detail"], "- memorable": ["all three books are praised for their ability to stay with the reader long after the story is finished,"]}