{"plain": "Based on the user's favourite books, it can be inferred that the user enjoys:\nHistorical Fiction: The Mists of Avalon and The Other Boleyn Girl are set in medieval times, while Gods and Generals is a Civil War novel.\nFantasy: Son of a Witch and Wicked: The Life and Times of the Wicked Witch of the West are both fantasy novels.\nWell-crafted writing style: All of the books are highly rated and praised for their writing style.\nComplex plot: The books feature intricate plots with multiple subplots and character development.\nLonger length: Most of the books are over 400 pages, indicating a preference for longer novels.\nThematic depth: The books explore a variety of themes such as history, magic, and morality.\nNarrative structure: The books feature a mix of first-person and third-person narration, as well as multiple perspectives.\nIt can also be inferred that the user enjoys a good balance of action, dialogue, and descriptive writing. The books are known for their rich character development, political intrigue, and exploration of complex social issues. The user likely enjoys a good mix of humor and tragedy, as well as a satisfying ending that ties up loose ends while leaving some room for imagination and interpretation.", "based on the user's favourite books, it can be inferred that the user enjoys:\nhistorical fiction": ["the mists of avalon and the other boleyn girl are set in medieval times", "while gods and generals is a civil war novel"], "fantasy": ["son of a witch and wicked"], "well-crafted writing style": ["all of the books are highly rated and praised for their writing style"], "complex plot": ["the books feature intricate plots with multiple subplots and character development"], "longer length": ["most of the books are over 400 pages", "indicating a preference for longer novels"], "thematic depth": ["the books explore a variety of themes such as history", "magic", "and morality"], "narrative structure": ["the books feature a mix of first-person and third-person narration", "as well as multiple perspectives"]}