{"plain": "Based on the user's favourite books, it can be inferred that they enjoy reading works that are:\n- Literary classics: The user's favourites include \"King Lear\" by William Shakespeare and \"The Scarlet Letter\" by Nathaniel Hawthorne, which are considered literary classics.\n- Classic American literature: The user's favourites also include \"Go Down, Moses\" and \"The Sound and the Fury,\" both by William Faulkner, who is considered one of the greatest American writers.\n- Religious themes: \"The Scarlet Letter\" explores themes of sin, punishment, and redemption, while \"The Power and the Glory\" by Graham Greene is a novel that deals with religious themes.\n- Philosophical themes: \"King Lear\" is a play that explores themes of power, family, and the nature of humanity.\n\nIt can also be inferred that the user enjoys reading works that are:\n- Complex: The user's favourites include works that are considered complex in terms of plot, character development, and themes.\n- Thought-provoking: The user's favourites include works that are considered thought-provoking and that challenge the reader to consider different perspectives and ideas.\n- Multi-layered: The user's favourites include works that are considered multi-layered and that offer different interpretations and meanings.\n\nBased on the user's favourites, it can also be inferred that the user enjoys reading works that are:\n- Well-written: The user's favourites include works that are considered well-written in terms of language, style, and structure.\n- Rich in detail: The user's favourites include works that are considered rich in detail and that offer a deep and nuanced understanding of the characters, settings, and themes.\n\nIn summary, based on the user's favourites, it can be inferred that the user enjoys reading works that are literary classics, complex, thought-provoking, multi-layered, well-written, and rich in detail. The user also seems to enjoy reading works that explore philosophical and religious themes, as well as works that offer a deep and nuanced understanding of the characters, settings, and themes.", "based on the user's favourite books, it can be inferred that they enjoy reading works that are:\n- literary classics": ["the user's favourites include \"king lear\" by william shakespeare and \"the scarlet letter\" by nathaniel hawthorne", "which are considered literary classics"], "- classic american literature": ["the user's favourites also include \"go down", "moses\" and \"the sound and the fury,\" both by william faulkner", "who is considered one of the greatest american writers"], "- religious themes": ["\"the scarlet letter\" explores themes of sin", "punishment", "and redemption", "while \"the power and the glory\" by graham greene is a novel that deals with religious themes"], "- philosophical themes": ["\"king lear\" is a play that explores themes of power", "family", "and the nature of humanity"], "it can also be inferred that the user enjoys reading works that are:\n- complex": ["the user's favourites include works that are considered complex in terms of plot", "character development", "and themes"], "- thought-provoking": ["the user's favourites include works that are considered thought-provoking and that challenge the reader to consider different perspectives and ideas"], "- multi-layered": ["the user's favourites include works that are considered multi-layered and that offer different interpretations and meanings"], "based on the user's favourites, it can also be inferred that the user enjoys reading works that are:\n- well-written": ["the user's favourites include works that are considered well-written in terms of language", "style", "and structure"], "- rich in detail": ["the user's favourites include works that are considered rich in detail and that offer a deep and nuanced understanding of the characters", "settings", "and themes"]}