{"plain": "Based on the user's favourite books, it can be inferred that the user enjoys:\n- Literary fiction: Both \"Ladder of Years\" and \"The Poisonwood Bible\" are considered literary fiction, known for their complex characters and themes.\n- Strong female protagonists: \"Ladder of Years\" features a strong female protagonist, a theme that is also present in \"The Poisonwood Bible\" to a lesser extent.\n- Exploration of social issues: Both books tackle social issues, such as poverty and religion, respectively.\n- Multigenerational storytelling: \"Ladder of Years\" follows a mother and her daughter, while \"The Poisonwood Bible\" is told from the perspective of a mother and her daughters.\n- International settings: \"The Poisonwood Bible\" is set in the Congo, providing a unique perspective on a complex historical event.\n\nBased on the user's preferences, it can be inferred that they likely enjoy:\n- Character-driven stories: The user's favourite books are known for their complex characters and exploration of social issues.\n- Thought-provoking themes: The user's favourite books tackle complex themes, such as poverty and religion.\n- Multigenerational storytelling: The user's favourite books feature multiple generations of characters, suggesting a preference for this storytelling device.\n- International settings: \"The Poisonwood Bible\" is set in the Congo, suggesting a preference for stories that explore different cultures and perspectives.\n\nIn summary, based on the user's favourite books, it can be inferred that they enjoy literary fiction with strong female protagonists, exploration of social issues, multigenerational storytelling, and international settings. Additionally, it can be inferred that they likely enjoy character-driven stories, thought-provoking themes, and multigenerational storytelling.", "based on the user's favourite books, it can be inferred that the user enjoys:\n- literary fiction": ["both \"ladder of years\" and \"the poisonwood bible\" are considered literary fiction", "known for their complex characters and themes"], "- strong female protagonists": ["\"ladder of years\" features a strong female protagonist", "a theme that is also present in \"the poisonwood bible\" to a lesser extent"], "- exploration of social issues": ["both books tackle social issues", "such as poverty and religion", "respectively"], "- multigenerational storytelling": ["the user's favourite books feature multiple generations of characters", "suggesting a preference for this storytelling device"], "- international settings": ["\"the poisonwood bible\" is set in the congo", "suggesting a preference for stories that explore different cultures and perspectives"], "based on the user's preferences, it can be inferred that they likely enjoy:\n- character-driven stories": ["the user's favourite books are known for their complex characters and exploration of social issues"], "- thought-provoking themes": ["the user's favourite books tackle complex themes", "such as poverty and religion"]}