{"plain": "Based on the user's favourite books, it can be inferred that they enjoy reading books with the following features:\n\nGenre: The user appears to have a preference for fiction books, as all of their favourites are novels.\n\nPlot: The user seems to enjoy books with complex and thought-provoking plots, as evidenced by the variety of themes and topics covered in their favourites.\n\nSetting: The user's favourites span a range of settings, from historical fiction to contemporary stories, suggesting a preference for diverse and immersive settings.\n\nWriting Style: The user appears to appreciate a range of writing styles, from lyrical and descriptive to more straightforward and plot-driven.\n\nLength: The user's favourites vary in length, from shorter novels to longer epics, suggesting a preference for books of different lengths.\n\nTopic: The user's favourites cover a wide range of topics, from historical fiction to coming-of-age stories, suggesting a preference for diverse and engaging topics.\n\nPacing: The user's favourites appear to have a good balance of action and reflection, suggesting a preference for a well-paced narrative.\n\nNarrative Structure: The user's favourites feature a variety of narrative structures, from linear to non-linear, suggesting a preference for diverse and engaging storytelling techniques.\n\nThemes: The user's favourites cover a range of themes, from social justice to family dynamics, suggesting a preference for books that tackle complex and meaningful themes.\n\nBased on the user's preferences, it is likely that they enjoy books that challenge them intellectually and emotionally, offering a rich and immersive reading experience.", "based on the user's favourite books, it can be inferred that they enjoy reading books with the following features:\n\ngenre": ["the user appears to have a preference for fiction books", "as all of their favourites are novels"], "plot": ["the user seems to enjoy books with complex and thought-provoking plots", "as evidenced by the variety of themes and topics covered in their favourites"], "setting": ["the user's favourites span a range of settings", "from historical fiction to contemporary stories", "suggesting a preference for diverse and immersive settings"], "writing style": ["the user appears to appreciate a range of writing styles", "from lyrical and descriptive to more straightforward and plot-driven"], "length": ["the user's favourites vary in length", "from shorter novels to longer epics", "suggesting a preference for books of different lengths"], "topic": ["the user's favourites cover a wide range of topics", "from historical fiction to coming-of-age stories", "suggesting a preference for diverse and engaging topics"], "pacing": ["the user's favourites appear to have a good balance of action and reflection", "suggesting a preference for a well-paced narrative"], "narrative structure": ["the user's favourites feature a variety of narrative structures", "from linear to non-linear", "suggesting a preference for diverse and engaging storytelling techniques"], "themes": ["the user's favourites cover a range of themes", "from social justice to family dynamics", "suggesting a preference for books that tackle complex and meaningful themes"]}