{"plain": "Based on the user's favourite books, it can be inferred that they enjoy reading books with the following features:\n\nGenre: The user seems to have a preference for books that fall under the LGBTQ+ and young adult genres.\n\nPlot: The user appears to enjoy books with complex and thought-provoking plots, often exploring themes of identity, relationships, and social issues.\n\nSetting: The user seems to have a fondness for books set in a variety of locations, including contemporary and historical settings, as well as fictional worlds.\n\nWriting Style: The user seems to appreciate books with a range of writing styles, from realistic and raw to imaginative and magical.\n\nLength: The user does not seem to have a preference for books of a particular length, as their favourite books vary in length from short stories to full-length novels.\n\nTopic: The user appears to enjoy books that explore a variety of topics, including coming-of-age, romance, fantasy, and social justice.\n\nPacing: The user seems to enjoy books with a range of pacing, from fast-paced and action-packed to slow-burning and introspective.\n\nNarrative Structure: The user seems to appreciate books with a variety of narrative structures, from linear and chronological to non-linear and non-chronological.\n\nThemes: The user appears to enjoy books that explore a range of themes, including identity, relationships, social justice, and personal growth.\n\nBased on the user's favourite books, it can be inferred that they have a broad range of interests and enjoy reading books that challenge and expand their understanding of the world.", "based on the user's favourite books, it can be inferred that they enjoy reading books with the following features:\n\ngenre": ["the user seems to have a preference for books that fall under the lgbtq+ and young adult genres"], "plot": ["the user appears to enjoy books with complex and thought-provoking plots", "often exploring themes of identity", "relationships", "and social issues"], "setting": ["the user seems to have a fondness for books set in a variety of locations", "including contemporary and historical settings", "as well as fictional worlds"], "writing style": ["the user seems to appreciate books with a range of writing styles", "from realistic and raw to imaginative and magical"], "length": ["the user does not seem to have a preference for books of a particular length", "as their favourite books vary in length from short stories to full-length novels"], "topic": ["the user appears to enjoy books that explore a variety of topics", "including coming-of-age", "romance", "fantasy", "and social justice"], "pacing": ["the user seems to enjoy books with a range of pacing", "from fast-paced and action-packed to slow-burning and introspective"], "narrative structure": ["the user seems to appreciate books with a variety of narrative structures", "from linear and chronological to non-linear and non-chronological"], "themes": ["the user appears to enjoy books that explore a range of themes", "including identity", "relationships", "social justice", "and personal growth"]}