{"plain": "Based on the user's favourite books, it can be inferred that the user enjoys:\n- Historical fiction: The Age of Innocence and Water for Elephants are set in the past.\n- Fantasy: Jonathan Strange & Mr Norrell is a fantasy novel.\n- Mystery: The Ruby in the Smoke is a mystery novel.\n- Classic literature: The Age of Innocence is a classic novel.\n- Shorter books: The Ruby in the Smoke is a shorter book compared to the others.\n- Well-written books: All of the user's favourite books are well-written and have received critical acclaim.\n\nIt can also be inferred that the user enjoys:\n- Complex plots: All of the user's favourite books have complex plots.\n- Well-developed characters: All of the user's favourite books have well-developed characters.\n- Richly described settings: All of the user's favourite books have richly described settings.\n- Elegant writing style: The Age of Innocence is known for its elegant writing style.\n- Emotional themes: All of the user's favourite books explore emotional themes.\n- Thought-provoking narratives: All of the user's favourite books are thought-provoking.\n\nIn summary, the user enjoys complex, well-written historical fiction, fantasy, and mystery novels with well-developed characters, richly described settings, elegant writing style, and thought-provoking narratives that explore emotional themes.", "based on the user's favourite books, it can be inferred that the user enjoys:\n- historical fiction": ["the age of innocence and water for elephants are set in the past"], "- fantasy": ["jonathan strange & mr norrell is a fantasy novel"], "- mystery": ["the ruby in the smoke is a mystery novel"], "- classic literature": ["the age of innocence is a classic novel"], "- shorter books": ["the ruby in the smoke is a shorter book compared to the others"], "- well-written books": ["all of the user's favourite books are well-written and have received critical acclaim"], "it can also be inferred that the user enjoys:\n- complex plots": ["all of the user's favourite books have complex plots"], "- well-developed characters": ["all of the user's favourite books have well-developed characters"], "- richly described settings": ["all of the user's favourite books have richly described settings"], "- elegant writing style": ["the age of innocence is known for its elegant writing style"], "- emotional themes": ["all of the user's favourite books explore emotional themes"], "- thought-provoking narratives": ["all of the user's favourite books are thought-provoking"]}