{"plain": "Based on the user's favorite movies, it can be inferred that they have a fondness for:\n- Fantasy/Adventure: Movies such as \"Aladdin,\" \"The Princess Bride,\" and \"The Jungle Book\" fall into this category.\n- Musical: \"Singin' in the Rain,\" \"An American in Paris,\" and \"My Fair Lady\" are all musicals.\n- Classic Hollywood: \"Snow White and the Seven Dwarfs,\" \"Cinderella,\" and \"Mary Poppins\" are all classic Hollywood films.\n- Disney: \"The Little Mermaid,\" \"Pete's Dragon,\" and \"Bedknobs and Broomsticks\" are all Disney movies.\n- Animation: \"Fantasia,\" \"Anastasia,\" and \"A Bug's Life\" are all animated films.\n- Comedy: \"National Lampoon's Animal House,\" \"Auntie Mame,\" and \"Bull Durham\" are all comedies.\n- Classic Literature Adaptations: \"A Kid in King Arthur's Court,\" \"My Fair Lady,\" and \"Shakespeare in Love\" are all adaptations of classic literature.\n- Classic Cinema: \"Roman Holiday,\" \"Bringing Up Baby,\" and \"Holiday Inn\" are all classic cinema films.\n- Science Fiction/Fantasy: \"Star Wars Episode V: The Empire Strikes Back,\" \"Galaxy Quest,\" and \"Fantasia 2000\" fall into this category.\n- Classic Drama: \"Cool Hand Luke,\" \"West Side Story,\" and \"South Pacific\" are all classic dramas.\n\nBased on the user's favorite movies, it can also be inferred that they likely enjoy:\n- Imaginative and adventurous storytelling.\n- Classic and timeless themes and stories.\n- Musical scores and songs.\n- Animation and visual creativity.\n- Humor and lightheartedness.\n- Fantasy and science fiction elements.\n- Classic film and drama styles.\n\nOverall, the user's taste seems to be diverse and well-rounded, with a fondness for many different genres and styles of film.", "based on the user's favorite movies, it can be inferred that they have a fondness for:\n- fantasy/adventure": ["movies such as \"aladdin,\" \"the princess bride,\" and \"the jungle book\" fall into this category"], "- musical": ["\"singin' in the rain,\" \"an american in paris,\" and \"my fair lady\" are all musicals"], "- classic hollywood": ["\"snow white and the seven dwarfs,\" \"cinderella,\" and \"mary poppins\" are all classic hollywood films"], "- disney": ["\"the little mermaid,\" \"pete's dragon,\" and \"bedknobs and broomsticks\" are all disney movies"], "- animation": ["\"fantasia,\" \"anastasia,\" and \"a bug's life\" are all animated films"], "- comedy": ["\"national lampoon's animal house,\" \"auntie mame,\" and \"bull durham\" are all comedies"], "- classic literature adaptations": ["\"a kid in king arthur's court,\" \"my fair lady,\" and \"shakespeare in love\" are all adaptations of classic literature"], "- classic cinema": ["\"roman holiday,\" \"bringing up baby,\" and \"holiday inn\" are all classic cinema films"], "- science fiction/fantasy": ["\"star wars episode v"], "- classic drama": ["\"cool hand luke,\" \"west side story,\" and \"south pacific\" are all classic dramas"]}