{"plain": " Most likely, the user enjoys movies that are:\n- Dramatic: The user likes movies like The Remains of the Day, Schindler's List, The Bridge on the River Kwai, Raise the Red Lantern, Gandhi, The Last Emperor, Exorcist: The Beginning, Saving Private Ryan, Shakespeare in Love, American Beauty, Being John Malkovich, Dogma, The Natural, and National Lampoon's Animal House.\n- Comedic: The user likes movies like Some Like It Hot, Casablanca, Gone with the Wind, It's a Wonderful Life, and Ghostbusters.\n- Action: The user likes movies like Pulp Fiction, The Shawshank Redemption, Platoon, Apocalypse Now, Goodfellas, The Godfather Part II, Full Metal Jacket, Jaws, and Auntie Mame.\n- Fantasy: The user likes movies like Fantasia and The Sixth Sense.\n- Horror: The user likes movies like The Exorcist.\n- Historical: The user likes movies like Schindler's List, The Last Emperor, and Saving Private Ryan.\n- Biographical: The user likes movies like Gandhi and The Last Emperor.\n- War: The user likes movies like Saving Private Ryan and The Bridge on the River Kwai.\n- Philosophical: The user likes movies like Dogma and The Natural.\n- Satirical: The user likes movies like National Lampoon's Animal House and Auntie Mame.\n- Romantic: The user likes movies like Gone with the Wind and Shakespeare in Love.\n- Family: The user likes movies like It's a Wonderful Life and Ghostbusters.\n- Supernatural: The user likes movies like The Sixth Sense.\n- Psychological: The user likes movies like American Beauty and Being John Malkovich.\n- Religious: The user likes movies like Dogma.\n- Political: The user likes movies like To Kill a Mockingbird and The Remains of the Day.\n- Musical: The user likes movies like Some Like It Hot and Casablanca.\n- Period: The user likes movies like Gone with the Wind, It's a Wonderful Life, and Auntie Mame.\n- Mystery: The user likes movies like To Kill a Mockingbird and The Sixth Sense.\n- Adventure: The user likes movies like The Bridge on the River Kwai and The Last Emperor.\n- Science Fiction: The user likes movies like Fantasia.\n- Western: The user likes movies like Gone with the Wind and Auntie Mame.\n- Crime: The user likes movies like Pulp Fiction,", "most likely, the user enjoys movies that are:\n- dramatic": ["the user likes movies like the remains of the day", "schindler's list", "the bridge on the river kwai", "raise the red lantern", "gandhi", "the last emperor", "exorcist"], "- comedic": ["the user likes movies like some like it hot", "casablanca", "gone with the wind", "it's a wonderful life", "and ghostbusters"], "- action": ["the user likes movies like pulp fiction", "the shawshank redemption", "platoon", "apocalypse now", "goodfellas", "the godfather part ii", "full metal jacket", "jaws", "and auntie mame"], "- fantasy": ["the user likes movies like fantasia and the sixth sense"], "- horror": ["the user likes movies like the exorcist"], "- historical": ["the user likes movies like schindler's list", "the last emperor", "and saving private ryan"], "- biographical": ["the user likes movies like gandhi and the last emperor"], "- war": ["the user likes movies like saving private ryan and the bridge on the river kwai"], "- philosophical": ["the user likes movies like dogma and the natural"], "- satirical": ["the user likes movies like national lampoon's animal house and auntie mame"], "- romantic": ["the user likes movies like gone with the wind and shakespeare in love"], "- family": ["the user likes movies like it's a wonderful life and ghostbusters"], "- supernatural": ["the user likes movies like the sixth sense"], "- psychological": ["the user likes movies like american beauty and being john malkovich"], "- religious": ["the user likes movies like dogma"], "- political": ["the user likes movies like to kill a mockingbird and the remains of the day"], "- musical": ["the user likes movies like some like it hot and casablanca"], "- period": ["the user likes movies like gone with the wind", "it's a wonderful life", "and auntie mame"], "- mystery": ["the user likes movies like to kill a mockingbird and the sixth sense"], "- adventure": ["the user likes movies like the bridge on the river kwai and the last emperor"], "- science fiction": ["the user likes movies like fantasia"], "- western": ["the user likes movies like gone with the wind and auntie mame"], "- crime": ["the user likes movies like pulp fiction,"]}