{"plain": "Based on the user's favourite movies, it can be inferred that the user enjoys:\nDrama: The English Patient, The Cider House Rules, The Talented Mr. Ripley\nMystery: Manhattan Murder Mystery, Rear Window, L.A. Confidential, Klute, Simon Birch, Central Station, Radio Days, Moonstruck\nThriller: The Fugitive, Blue Velvet\nRomance: Annie Hall, Moonstruck\nAdaptations: The English Patient, The Cider House Rules, The Talented Mr. Ripley, Annie Hall, Moonstruck, Simon Birch, Central Station, Radio Days\nPeriod Pieces: The English Patient, The Cider House Rules, The Talented Mr. Ripley, Annie Hall, Moonstruck, Simon Birch, Central Station, Radio Days\nVisual Style: The English Patient, The Cider House Rules, The Talented Mr. Ripley, Annie Hall, Moonstruck, Simon Birch, Central Station, Radio Days\nWriting Style: The English Patient, The Cider House Rules, The Talented Mr. Ripley, Annie Hall, Moonstruck, Simon Birch, Central Station, Radio Days\nRuntime: The English Patient, The Cider House Rules, The Talented Mr. Ripley, Annie Hall, Moonstruck, Simon Birch, Central Station, Radio Days\nThemes: The English Patient, The Cider House Rules, The Talented Mr. Ripley, Annie Hall, Moonstruck, Simon Birch, Central Station, Radio Days\n\nIt can also be inferred that the user enjoys movies with complex and well-developed characters, as many of their favourite movies feature characters that undergo significant development over the course of the story. The user also seems to enjoy movies that tackle difficult and thought-provoking themes, as many of their favourite movies deal with weighty subjects such as war, identity, and relationships.", "based on the user's favourite movies, it can be inferred that the user enjoys:\ndrama": ["the english patient", "the cider house rules", "the talented mr"], "ripley\nmystery": ["manhattan murder mystery", "rear window", "l"], "confidential, klute, simon birch, central station, radio days, moonstruck\nthriller": ["the fugitive", "blue velvet\nromance"], "ripley, annie hall, moonstruck, simon birch, central station, radio days\nperiod pieces": ["the english patient", "the cider house rules", "the talented mr"], "ripley, annie hall, moonstruck, simon birch, central station, radio days\nvisual style": ["the english patient", "the cider house rules", "the talented mr"], "ripley, annie hall, moonstruck, simon birch, central station, radio days\nwriting style": ["the english patient", "the cider house rules", "the talented mr"], "ripley, annie hall, moonstruck, simon birch, central station, radio days\nruntime": ["the english patient", "the cider house rules", "the talented mr"], "ripley, annie hall, moonstruck, simon birch, central station, radio days\nthemes": ["the english patient", "the cider house rules", "the talented mr"]}