{"plain": "Based on the list of favorite movies provided, it can be inferred that the user has diverse and eclectic tastes in film. They seem to enjoy a mix of classic and modern movies, spanning various genres and styles. Some common themes or elements that can be observed in the list include:\n\n- Appreciation for classic films: The list includes many iconic and well-known movies from the Golden Age of Hollywood, as well as influential foreign films and cult classics.\n- Variety in genre: The user's taste seems to extend beyond a single genre, as the list includes dramas, comedies, horror, science fiction, westerns, and more.\n- Preference for character-driven stories: Many of the movies on the list are known for their strong characters and compelling narratives, rather than solely for their technical aspects or groundbreaking innovations.\n- Appreciation for visual style: The list includes movies with distinctive and memorable visual styles, whether it be the iconic black-and-white cinematography of classic films or the more experimental approaches taken by modern filmmakers.\n- Enjoyment of longer runtimes: While not a hard and fast rule, many of the movies on the list have a runtime of over 2 hours, suggesting that the user may prefer more in-depth and immersive storytelling experiences.\n\nOverall, the user's taste in film appears to be well-rounded and open-minded, with a deep appreciation for the art form and its many iterations and expressions.", "some common themes or elements that can be observed in the list include:\n\n- appreciation for classic films": ["the list includes many iconic and well-known movies from the golden age of hollywood", "as well as influential foreign films and cult classics"], "- variety in genre": ["the user's taste seems to extend beyond a single genre", "as the list includes dramas", "comedies", "horror", "science fiction", "westerns", "and more"], "- preference for character-driven stories": ["many of the movies on the list are known for their strong characters and compelling narratives", "rather than solely for their technical aspects or groundbreaking innovations"], "- appreciation for visual style": ["the list includes movies with distinctive and memorable visual styles", "whether it be the iconic black-and-white cinematography of classic films or the more experimental approaches taken by modern filmmakers"], "- enjoyment of longer runtimes": ["while not a hard and fast rule", "many of the movies on the list have a runtime of over 2 hours", "suggesting that the user may prefer more in-depth and immersive storytelling experiences"]}