{"plain": " Powder is a science fiction movie, Quiz Show is a drama, The Shawshank Redemption is a drama, The Client is a legal drama, Forrest Gump is a drama, Dave is a comedy, Schindler's List is a drama, Searching for Bobby Fischer is a drama, My Fair Lady is a musical, E.T. the Extra-Terrestrial is a science fiction movie, The Princess Bride is a fantasy, Amadeus is a drama, When Harry Met Sally... is a romantic comedy, The Full Monty is a comedy, Titanic is a drama, Out of Africa is a drama, The Breakfast Club is a drama, The Poseidon Adventure is an adventure movie, Elizabeth is a historical drama, Meet Joe Black is a drama, The Prince of Egypt is an animated movie, Shakespeare in Love is a romantic comedy, The King and I is a musical, The Color Purple is a drama, The Sixth Sense is a horror movie, Mumford is a comedy, Toy Story 2 is an animated movie, and Close Encounters of the Third Kind is a science fiction movie.\n\nThe user's favourite genre is likely to be drama, science fiction, comedy, or a combination of these. The user's favourite kind of plot is likely to be a combination of the following: legal, historical, fantasy, adventure, musical, and horror. The user's favourite kind of musical score is likely to be dramatic, epic, or a combination of these. The user's favourite mood for the musical score is likely to be serious, epic, or a combination of these. The user's favourite setting is likely to be a combination of the following: historical, fictional, and modern. The user's favourite visual style is likely to be a combination of the following: realistic, animated, and fantasy. The user's favourite writing style is likely to be a combination of the following: serious, comedic, and dramatic. The user's favourite runtime is likely to be between 90 and 180 minutes. The user's favourite themes are likely to be a combination of the following: coming of age, self-discovery, and overcoming adversity.", "the user's favourite kind of plot is likely to be a combination of the following": ["legal", "historical", "fantasy", "adventure", "musical", "and horror"], "the user's favourite setting is likely to be a combination of the following": ["historical", "fictional", "and modern"], "the user's favourite visual style is likely to be a combination of the following": ["realistic", "animated", "and fantasy"], "the user's favourite writing style is likely to be a combination of the following": ["serious", "comedic", "and dramatic"], "the user's favourite themes are likely to be a combination of the following": ["coming of age", "self-discovery", "and overcoming adversity"]}