{"plain": "Based on the user's favourite movies, it can be inferred that their favourite genre is action, as evidenced by movies such as Jurassic Park, Terminator 2: Judgment Day, Die Hard, The Matrix, and Star Wars Episode I: The Phantom Menace. Additionally, the user likely enjoys movies with a mix of drama and comedy, as seen in movies like A Fish Called Wanda, Heathers, Sling Blade, The Fifth Element, Dark City, Deep Impact, Rocky, The Breakfast Club, Lethal Weapon, Beetlejuice, The Thing, Antz, Romancing the Stone, Jumpin' Jack Flash, Risky Business, Total Recall, Trading Places, Fatal Attraction, Fast Times at Ridgemont High, The Outlaw Josey Wales, Arthur, and U-571. The user's favourite kind of plot is likely to be complex and multi-layered, as seen in movies like Coneheads, Jurassic Park, Terminator 2: Judgment Day, Die Hard, A Fish Called Wanda, E.T. the Extra-Terrestrial, The Good, the Bad and the Ugly, Heathers, Sling Blade, The Fifth Element, Dark City, Deep Impact, Rocky, The Breakfast Club, Lethal Weapon, Beetlejuice, The Thing, Antz, Romancing the Stone, Jumpin' Jack Flash, The Matrix, Star Wars Episode I: The Phantom Menace, Ghostbusters, RV, Risky Business, Total Recall, Trading Places, Fatal Attraction, Fast Times at Ridgemont High, The Outlaw Josey Wales, Arthur, and U-571. The user's favourite kind of musical score is likely to be epic and grand, as seen in movies like Jurassic Park, Terminator 2: Judgment Day, Die Hard, The Matrix, Star Wars Episode I: The Phantom Menace, Ghostbusters, RV, Risky Business, Total Recall, Trading Places, Fatal Attraction, Fast Times at Ridgemont High, The Outlaw Josey Wales, Arthur, and U-571. The user's favourite mood for the musical score is likely to be intense and action-packed, as seen in movies like Jurassic Park, Terminator 2: Judgment Day, Die Hard, The Matrix, Star Wars Episode I: The Phantom Menace, Ghostbusters, RV, Risky Business, Total Recall, Trading Places, Fatal Attraction, Fast Times at Ridgemont High, The Outlaw Josey Wales, Arthur, and U-571. The user's favourite setting", "based on the user's favourite movies, it can be inferred that their favourite genre is action, as evidenced by movies such as jurassic park, terminator 2": ["judgment day", "die hard", "the matrix", "and star wars episode i"], "the user's favourite kind of plot is likely to be complex and multi-layered, as seen in movies like coneheads, jurassic park, terminator 2": ["judgment day", "die hard", "a fish called wanda", "e"], "the extra-terrestrial, the good, the bad and the ugly, heathers, sling blade, the fifth element, dark city, deep impact, rocky, the breakfast club, lethal weapon, beetlejuice, the thing, antz, romancing the stone, jumpin' jack flash, the matrix, star wars episode i": ["the phantom menace", "ghostbusters", "rv", "risky business", "total recall", "trading places", "fatal attraction", "fast times at ridgemont high", "the outlaw josey wales", "arthur", "and u-571"], "the user's favourite kind of musical score is likely to be epic and grand, as seen in movies like jurassic park, terminator 2": ["judgment day", "die hard", "the matrix", "star wars episode i"], "the user's favourite mood for the musical score is likely to be intense and action-packed, as seen in movies like jurassic park, terminator 2": ["judgment day", "die hard", "the matrix", "star wars episode i"]}