{"plain": " Vertigo, Rear Window, North by Northwest, The Birds, Psycho, The Sixth Sense, and Sling Blade are all examples of thrillers. The Wizard of Oz, Mary Poppins, The Sound of Music, and West Side Story are examples of musicals. Notorious, Strangers on a Train, and Outrageous Fortune are examples of mysteries. The user's favourite genre is likely to be a combination of these three.\n\nThe user's favourite kind of plot is likely to be a combination of the three main types of plots: man vs. man, man vs. nature, and man vs. self. The user's favourite kind of musical score is likely to be a combination of the three main types of musical scores: orchestral, choral, and solo instrumental. The user's favourite mood for the musical score is likely to be a combination of the three main moods: happy, sad, and scary.\n\nThe user's favourite setting is likely to be a combination of the three main settings: city, countryside, and fantasy. The user's favourite visual style is likely to be a combination of the three main visual styles: realistic, cartoonish, and futuristic. The user's favourite writing style is likely to be a combination of the three main writing styles: descriptive, expository, and narrative. The user's favourite runtime is likely to be a combination of the three main runtimes: short, medium, and long.\n\nThe user's favourite themes are likely to be a combination of the three main themes: love, war, and death.", "the user's favourite kind of plot is likely to be a combination of the three main types of plots": ["man vs"], "the user's favourite kind of musical score is likely to be a combination of the three main types of musical scores": ["orchestral", "choral", "and solo instrumental"], "the user's favourite mood for the musical score is likely to be a combination of the three main moods": ["happy", "sad", "and scary"], "the user's favourite setting is likely to be a combination of the three main settings": ["city", "countryside", "and fantasy"], "the user's favourite visual style is likely to be a combination of the three main visual styles": ["realistic", "cartoonish", "and futuristic"], "the user's favourite writing style is likely to be a combination of the three main writing styles": ["descriptive", "expository", "and narrative"], "the user's favourite runtime is likely to be a combination of the three main runtimes": ["short", "medium", "and long"], "the user's favourite themes are likely to be a combination of the three main themes": ["love", "war", "and death"]}