{"plain": "Based on the user's favorite movies, it can be inferred that their favorite genre is action, as Terminator 2: Judgment Day, An American Werewolf in London, and Boiler Room are all action films. Additionally, the user likely enjoys films with a plot that is both entertaining and thought-provoking, as evidenced by the inclusion of The Princess Bride and The General's Daughter in their list of favorites. The user also seems to prefer films with a musical score that is both memorable and fitting for the mood and setting of the film, as seen in The Sound of Music and Jaws. The user's favorite mood for the musical score is likely to be suspenseful or dramatic, as these are common moods associated with action and thriller films. The user's favorite setting is likely to be a combination of both modern and historical settings, as seen in Terminator 2: Judgment Day and The Sound of Music. The user's favorite visual style is likely to be a combination of both realistic and stylized visuals, as seen in Terminator 2: Judgment Day and The Princess Bride. The user's favorite writing style is likely to be a combination of both humorous and serious writing styles, as seen in The Naked Gun: From the Files of Police Squad! and The General's Daughter. The user's favorite runtime is likely to be between 90 minutes and 120 minutes, as most of their favorite films fall within this range. The user's favorite themes are likely to be a combination of both action and drama, as seen in Terminator 2: Judgment Day and The General's Daughter.", "based on the user's favorite movies, it can be inferred that their favorite genre is action, as terminator 2": ["judgment day", "an american werewolf in london", "and boiler room are all action films"], "the user's favorite setting is likely to be a combination of both modern and historical settings, as seen in terminator 2": ["judgment day and the sound of music"], "the user's favorite visual style is likely to be a combination of both realistic and stylized visuals, as seen in terminator 2": ["judgment day and the princess bride"], "the user's favorite writing style is likely to be a combination of both humorous and serious writing styles, as seen in the naked gun": ["from the files of police squad! and the general's daughter"], "the user's favorite themes are likely to be a combination of both action and drama, as seen in terminator 2": ["judgment day and the general's daughter"]}